{"ResultSet": {"apiVersion": "1.27.0.0", "engineVersion": "202511_02a", "TimeTable": {"Station": {"Name": "舞鶴一丁目／西鉄バス"}, "Line": [{"trainID": "0", "Name": "２・普通・西新－次郎丸", "ArrivalState": {"Datetime": {"text": "06:36:00+09:00", "operation": "today"}}, "Destination": {"Station": {"code": "675273", "Name": "四箇田団地／西鉄バス"}}, "DepartureState": {"Datetime": {"text": "06:34:00+09:00", "operation": "today"}}}, {"trainID": "1", "Name": "３２・普通・志免－亀山－空港通博多駅－昭和通天神", "ArrivalState": {"Datetime": {"text": "06:36:00+09:00", "operation": "today"}}, "Destination": {"Station": {"code": "676853", "Name": "大濠公園／西鉄バス"}}, "DepartureState": {"Datetime": {"text": "06:34:00+09:00", "operation": "today"}}}, {"trainID": "2", "Name": "２３Ｎ・普通・海岸通り－都高－昭和通－天神", "ArrivalState": {"Datetime": {"text": "06:45:00+09:00", "operation": "today"}}, "Destination": {"Station": {"code": "676853", "Name": "大濠公園／西鉄バス"}}, "DepartureState": {"Datetime": {"text": "06:43:00+09:00", "operation": "today"}}}, {"trainID": "3", "Name": "２－３・普通・西新", "ArrivalState": {"Datetime": {"text": "06:53:00+09:00", "operation": "today"}}, "Destination": {"Station": {"code": "675471", "Name": "室住団地／西鉄バス"}}, "DepartureState": {"Datetime": {"text": "06:51:00+09:00", "operation": "today"}}}, {"trainID": "4", "Name": "３４・普通・志免－亀山－妙見－昭和通－天神", "ArrivalState": {"Datetime": {"text": "07:08:00+09:00", "operation": "today"}}, "Destination": {"Station": {"code": "676853", "Name": "大濠公園／西鉄バス"}}, "DepartureState": {"Datetime": {"text": "07:06:00+09:00", "operation": "today"}}}, {"trainID": "5", "Name": "２７Ｎ・普通・香椎東小－運輸支局－都高－天神", "ArrivalState": {"Datetime": {"text": "07:10:00+09:00", "operation": "today"}}, "Destination": {"Station": {"code": "676853", "Name": "大濠公園／西鉄バス"}}, "DepartureState": {"Datetime": {"text": "07:08:00+09:00", "operation": "today"}}}, {"trainID": "6", "Name": "２３Ｎ・普通・海岸通り－都高－昭和通－天神", "ArrivalState": {"Datetime": {"text": "07:15:00+09:00", "operation": "today"}}, "Destination": {"Station": {"code": "676853", "Name": "大濠公園／西鉄バス"}}, "DepartureState": {"Datetime": {"text": "07:13:00+09:00", "operation": "today"}}}, {"trainID": "7", "Name": "２３Ｂ・普通", "ArrivalState": {"Datetime": {"text": "07:18:00+09:00", "operation": "today"}}, "Destination": {"Station": {"code": "676853", "Name": "大濠公園／西鉄バス"}}, "DepartureState": {"Datetime": {"text": "07:16:00+09:00", "operation": "today"}}}, {"trainID": "8", "Name": "３２・普通・志免－亀山－空港通博多駅－昭和通天神", "ArrivalState": {"Datetime": {"text": "07:19:00+09:00", "operation": "today"}}, "Destination": {"Station": {"code": "676853", "Name": "大濠公園／西鉄バス"}}, "DepartureState": {"Datetime": {"text": "07:17:00+09:00", "operation": "today"}}}, {"trainID": "9", "Name": "２７Ｎ・普通・香椎東小－運輸支局－都高－天神", "ArrivalState": {"Datetime": {"text": "07:31:00+09:00", "operation": "today"}}, "Destination": {"Station": {"code": "676853", "Name": "大濠公園／西鉄バス"}}, "DepartureState": {"Datetime": {"text": "07:29:00+09:00", "operation": "today"}}}, {"trainID": "10", "Name": "２－３・普通・西新－室住団地－橋本", "ArrivalState": {"Datetime": {"text": "07:33:00+09:00", "operation": "today"}}, "Destination": {"Station": {"code": "675435", "Name": "野方(営業所)／西鉄バス"}}, "DepartureState": {"Datetime": {"text": "07:31:00+09:00", "operation": "today"}}}, {"trainID": "11", "Name": "２２Ｎ・普通・南公園－名島ランプ昭和通－天神", "ArrivalState": {"Datetime": {"text": "07:36:00+09:00", "operation": "today"}}, "Destination": {"Station": {"code": "676853", "Name": "大濠公園／西鉄バス"}}, "DepartureState": {"Datetime": {"text": "07:34:00+09:00", "operation": "today"}}}, {"trainID": "12", "Name": "２３Ｂ・普通", "ArrivalState": {"Datetime": {"text": "07:41:00+09:00", "operation": "today"}}, "Destination": {"Station": {"code": "676853", "Name": "大濠公園／西鉄バス"}}, "DepartureState": {"Datetime": {"text": "07:39:00+09:00", "operation": "today"}}}, {"trainID": "13", "Name": "２７Ｂ・普通・香椎参道－都高－昭和通－天神", "ArrivalState": {"Datetime": {"text": "07:41:00+09:00", "operation": "today"}}, "Destination": {"Station": {"code": "676853", "Name": "大濠公園／西鉄バス"}}, "DepartureState": {"Datetime": {"text": "07:39:00+09:00", "operation": "today"}}}, {"trainID": "14", "Name": "３４・普通・志免－亀山－妙見－昭和通－天神", "ArrivalState": {"Datetime": {"text": "07:43:00+09:00", "operation": "today"}}, "Destination": {"Station": {"code": "676853", "Name": "大濠公園／西鉄バス"}}, "DepartureState": {"Datetime": {"text": "07:41:00+09:00", "operation": "today"}}}, {"trainID": "15", "Name": "２・普通・西新－田隈新町－病院構内乗入", "ArrivalState": {"Datetime": {"text": "07:48:00+09:00", "operation": "today"}}, "Destination": {"Station": {"code": "678138", "Name": "歯科大病院(構内)／西鉄バス"}}, "DepartureState": {"Datetime": {"text": "07:46:00+09:00", "operation": "today"}}}, {"trainID": "16", "Name": "２３Ｎ・普通・海岸通り－都高－昭和通－天神", "ArrivalState": {"Datetime": {"text": "07:48:00+09:00", "operation": "today"}}, "Destination": {"Station": {"code": "676853", "Name": "大濠公園／西鉄バス"}}, "DepartureState": {"Datetime": {"text": "07:46:00+09:00", "operation": "today"}}}, {"trainID": "17", "Name": "３２・普通・志免－亀山－空港通博多駅－昭和通天神", "ArrivalState": {"Datetime": {"text": "07:48:00+09:00", "operation": "today"}}, "Destination": {"Station": {"code": "676853", "Name": "大濠公園／西鉄バス"}}, "DepartureState": {"Datetime": {"text": "07:46:00+09:00", "operation": "today"}}}, {"trainID": "18", "Name": "２７・普通・香椎参道－名島－昭和通－天神", "ArrivalState": {"Datetime": {"text": "07:51:00+09:00", "operation": "today"}}, "Destination": {"Station": {"code": "676853", "Name": "大濠公園／西鉄バス"}}, "DepartureState": {"Datetime": {"text": "07:49:00+09:00", "operation": "today"}}}, {"trainID": "19", "Name": "３２・普通・志免－亀山－空港通博多駅－昭和通天神", "ArrivalState": {"Datetime": {"text": "07:54:00+09:00", "operation": "today"}}, "Destination": {"Station": {"code": "676853", "Name": "大濠公園／西鉄バス"}}, "DepartureState": {"Datetime": {"text": "07:52:00+09:00", "operation": "today"}}}, {"trainID": "20", "Name": "４・普通・八田団地－千早駅－石堂大橋－昭和通", "ArrivalState": {"Datetime": {"text": "07:57:00+09:00", "operation": "today"}}, "Destination": {"Station": {"code": "676882", "Name": "福岡タワー(ＴＮＣ放送会館前)／西鉄バス"}}, "DepartureState": {"Datetime": {"text": "07:55:00+09:00", "operation": "today"}}}, {"trainID": "21", "Name": "２２Ｎ・普通・南公園－名島ランプ昭和通－天神", "ArrivalState": {"Datetime": {"text": "07:58:00+09:00", "operation": "today"}}, "Destination": {"Station": {"code": "676853", "Name": "大濠公園／西鉄バス"}}, "DepartureState": {"Datetime": {"text": "07:56:00+09:00", "operation": "today"}}}, {"trainID": "22", "Name": "２８Ｂ・普通・青葉台口－香椎参道－都高－天神", "ArrivalState": {"Datetime": {"text": "08:00:00+09:00", "operation": "today"}}, "Destination": {"Station": {"code": "676853", "Name": "大濠公園／西鉄バス"}}, "DepartureState": {"Datetime": {"text": "07:58:00+09:00", "operation": "today"}}}, {"trainID": "23", "Name": "３４・普通・志免－亀山－妙見－昭和通－天神", "ArrivalState": {"Datetime": {"text": "08:02:00+09:00", "operation": "today"}}, "Destination": {"Station": {"code": "676853", "Name": "大濠公園／西鉄バス"}}, "DepartureState": {"Datetime": {"text": "08:00:00+09:00", "operation": "today"}}}, {"trainID": "24", "Name": "２３Ｂ・普通", "ArrivalState": {"Datetime": {"text": "08:04:00+09:00", "operation": "today"}}, "Destination": {"Station": {"code": "676853", "Name": "大濠公園／西鉄バス"}}, "DepartureState": {"Datetime": {"text": "08:02:00+09:00", "operation": "today"}}}, {"trainID": "25", "Name": "２７Ｂ・普通・香椎参道－都高－昭和通－天神", "ArrivalState": {"Datetime": {"text": "08:05:00+09:00", "operation": "today"}}, "Destination": {"Station": {"code": "676853", "Name": "大濠公園／西鉄バス"}}, "DepartureState": {"Datetime": {"text": "08:03:00+09:00", "operation": "today"}}}, {"trainID": "26", "Name": "２７Ｎ・普通・香椎東小－運輸支局－都高－天神", "ArrivalState": {"Datetime": {"text": "08:08:00+09:00", "operation": "today"}}, "Destination": {"Station": {"code": "676853", "Name": "大濠公園／西鉄バス"}}, "DepartureState": {"Datetime": {"text": "08:06:00+09:00", "operation": "today"}}}, {"trainID": "27", "Name": "３２・普通・志免－亀山－空港通博多駅－昭和通天神", "ArrivalState": {"Datetime": {"text": "08:13:00+09:00", "operation": "today"}}, "Destination": {"Station": {"code": "676853", "Name": "大濠公園／西鉄バス"}}, "DepartureState": {"Datetime": {"text": "08:11:00+09:00", "operation": "today"}}}, {"trainID": "28", "Name": "２７０・普通・みどりが丘－香椎参道－都高", "ArrivalState": {"Datetime": {"text": "08:13:00+09:00", "operation": "today"}}, "Destination": {"Station": {"code": "676853", "Name": "大濠公園／西鉄バス"}}, "DepartureState": {"Datetime": {"text": "08:11:00+09:00", "operation": "today"}}}, {"trainID": "29", "Name": "３４・普通・志免－亀山－妙見－昭和通－天神", "ArrivalState": {"Datetime": {"text": "08:14:00+09:00", "operation": "today"}}, "Destination": {"Station": {"code": "676853", "Name": "大濠公園／西鉄バス"}}, "DepartureState": {"Datetime": {"text": "08:12:00+09:00", "operation": "today"}}}, {"trainID": "30", "Name": "２７・普通・香椎参道－名島－昭和通－天神", "ArrivalState": {"Datetime": {"text": "08:16:00+09:00", "operation": "today"}}, "Destination": {"Station": {"code": "676853", "Name": "大濠公園／西鉄バス"}}, "DepartureState": {"Datetime": {"text": "08:14:00+09:00", "operation": "today"}}}, {"trainID": "31", "Name": "２３Ｎ・普通・海岸通り－都高－昭和通－天神", "ArrivalState": {"Datetime": {"text": "08:18:00+09:00", "operation": "today"}}, "Destination": {"Station": {"code": "676853", "Name": "大濠公園／西鉄バス"}}, "DepartureState": {"Datetime": {"text": "08:16:00+09:00", "operation": "today"}}}, {"trainID": "32", "Name": "２－３・普通・西新－室住団地－橋本", "ArrivalState": {"Datetime": {"text": "08:23:00+09:00", "operation": "today"}}, "Destination": {"Station": {"code": "675435", "Name": "野方(営業所)／西鉄バス"}}, "DepartureState": {"Datetime": {"text": "08:21:00+09:00", "operation": "today"}}}, {"trainID": "33", "Name": "３４・普通・志免－亀山－妙見－昭和通－天神", "ArrivalState": {"Datetime": {"text": "08:23:00+09:00", "operation": "today"}}, "Destination": {"Station": {"code": "676853", "Name": "大濠公園／西鉄バス"}}, "DepartureState": {"Datetime": {"text": "08:21:00+09:00", "operation": "today"}}}, {"trainID": "34", "Name": "２８Ｂ・普通・青葉台口－香椎参道－都高－天神", "ArrivalState": {"Datetime": {"text": "08:25:00+09:00", "operation": "today"}}, "Destination": {"Station": {"code": "676853", "Name": "大濠公園／西鉄バス"}}, "DepartureState": {"Datetime": {"text": "08:23:00+09:00", "operation": "today"}}}, {"trainID": "35", "Name": "３２・普通・志免－亀山－空港通博多駅－昭和通天神", "ArrivalState": {"Datetime": {"text": "08:25:00+09:00", "operation": "today"}}, "Destination": {"Station": {"code": "676853", "Name": "大濠公園／西鉄バス"}}, "DepartureState": {"Datetime": {"text": "08:23:00+09:00", "operation": "today"}}}, {"trainID": "36", "Name": "２７Ｎ・普通・香椎東小－運輸支局－都高－天神", "ArrivalState": {"Datetime": {"text": "08:27:00+09:00", "operation": "today"}}, "Destination": {"Station": {"code": "676853", "Name": "大濠公園／西鉄バス"}}, "DepartureState": {"Datetime": {"text": "08:25:00+09:00", "operation": "today"}}}, {"trainID": "37", "Name": "２３Ｂ・普通", "ArrivalState": {"Datetime": {"text": "08:30:00+09:00", "operation": "today"}}, "Destination": {"Station": {"code": "676853", "Name": "大濠公園／西鉄バス"}}, "DepartureState": {"Datetime": {"text": "08:28:00+09:00", "operation": "today"}}}, {"trainID": "38", "Name": "２－３・普通・西新", "ArrivalState": {"Datetime": {"text": "08:33:00+09:00", "operation": "today"}}, "Destination": {"Station": {"code": "675471", "Name": "室住団地／西鉄バス"}}, "DepartureState": {"Datetime": {"text": "08:31:00+09:00", "operation": "today"}}}, {"trainID": "39", "Name": "２３Ｎ・普通・海岸通り－都高－昭和通－天神", "ArrivalState": {"Datetime": {"text": "08:33:00+09:00", "operation": "today"}}, "Destination": {"Station": {"code": "676853", "Name": "大濠公園／西鉄バス"}}, "DepartureState": {"Datetime": {"text": "08:31:00+09:00", "operation": "today"}}}, {"trainID": "40", "Name": "２７０・普通・みどりが丘－香椎参道－都高", "ArrivalState": {"Datetime": {"text": "08:33:00+09:00", "operation": "today"}}, "Destination": {"Station": {"code": "676853", "Name": "大濠公園／西鉄バス"}}, "DepartureState": {"Datetime": {"text": "08:31:00+09:00", "operation": "today"}}}, {"trainID": "41", "Name": "３４・普通・志免－亀山－妙見－昭和通－天神", "ArrivalState": {"Datetime": {"text": "08:35:00+09:00", "operation": "today"}}, "Destination": {"Station": {"code": "676853", "Name": "大濠公園／西鉄バス"}}, "DepartureState": {"Datetime": {"text": "08:33:00+09:00", "operation": "today"}}}, {"trainID": "42", "Name": "２８・普通・青葉台口－香椎参道名島－昭和通－天神", "ArrivalState": {"Datetime": {"text": "08:36:00+09:00", "operation": "today"}}, "Destination": {"Station": {"code": "676853", "Name": "大濠公園／西鉄バス"}}, "DepartureState": {"Datetime": {"text": "08:34:00+09:00", "operation": "today"}}}, {"trainID": "43", "Name": "４・普通・八田団地－千早駅－石堂大橋－昭和通", "ArrivalState": {"Datetime": {"text": "08:42:00+09:00", "operation": "today"}}, "Destination": {"Station": {"code": "676882", "Name": "福岡タワー(ＴＮＣ放送会館前)／西鉄バス"}}, "DepartureState": {"Datetime": {"text": "08:40:00+09:00", "operation": "today"}}}, {"trainID": "44", "Name": "２・普通・西新－田隈新町－福歯大病院", "ArrivalState": {"Datetime": {"text": "08:42:00+09:00", "operation": "today"}}, "Destination": {"Station": {"code": "675273", "Name": "四箇田団地／西鉄バス"}}, "DepartureState": {"Datetime": {"text": "08:40:00+09:00", "operation": "today"}}}, {"trainID": "45", "Name": "２８Ｂ・普通・青葉台口－香椎参道－都高－天神", "ArrivalState": {"Datetime": {"text": "08:43:00+09:00", "operation": "today"}}, "Destination": {"Station": {"code": "676853", "Name": "大濠公園／西鉄バス"}}, "DepartureState": {"Datetime": {"text": "08:41:00+09:00", "operation": "today"}}}, {"trainID": "46", "Name": "２３Ｎ・普通・海岸通り－都高－昭和通－天神", "ArrivalState": {"Datetime": {"text": "08:43:00+09:00", "operation": "today"}}, "Destination": {"Station": {"code": "676853", "Name": "大濠公園／西鉄バス"}}, "DepartureState": {"Datetime": {"text": "08:41:00+09:00", "operation": "today"}}}, {"trainID": "47", "Name": "２２Ｎ・普通・南公園－名島ランプ昭和通－天神", "ArrivalState": {"Datetime": {"text": "08:48:00+09:00", "operation": "today"}}, "Destination": {"Station": {"code": "676853", "Name": "大濠公園／西鉄バス"}}, "DepartureState": {"Datetime": {"text": "08:46:00+09:00", "operation": "today"}}}, {"trainID": "48", "Name": "３２・普通・志免－亀山－空港通博多駅－昭和通天神", "ArrivalState": {"Datetime": {"text": "08:49:00+09:00", "operation": "today"}}, "Destination": {"Station": {"code": "676853", "Name": "大濠公園／西鉄バス"}}, "DepartureState": {"Datetime": {"text": "08:47:00+09:00", "operation": "today"}}}, {"trainID": "49", "Name": "３４・普通・志免－亀山－妙見－昭和通－天神", "ArrivalState": {"Datetime": {"text": "08:50:00+09:00", "operation": "today"}}, "Destination": {"Station": {"code": "676853", "Name": "大濠公園／西鉄バス"}}, "DepartureState": {"Datetime": {"text": "08:48:00+09:00", "operation": "today"}}}, {"trainID": "50", "Name": "２８Ｂ・普通・青葉台口－香椎参道－都高－天神", "ArrivalState": {"Datetime": {"text": "08:53:00+09:00", "operation": "today"}}, "Destination": {"Station": {"code": "676853", "Name": "大濠公園／西鉄バス"}}, "DepartureState": {"Datetime": {"text": "08:51:00+09:00", "operation": "today"}}}, {"trainID": "51", "Name": "２－３・普通・西新－室住団地－橋本", "ArrivalState": {"Datetime": {"text": "08:53:00+09:00", "operation": "today"}}, "Destination": {"Station": {"code": "675435", "Name": "野方(営業所)／西鉄バス"}}, "DepartureState": {"Datetime": {"text": "08:51:00+09:00", "operation": "today"}}}, {"trainID": "52", "Name": "２３Ｎ・普通・香椎－海岸通り－名島ランプ－天神", "ArrivalState": {"Datetime": {"text": "08:57:00+09:00", "operation": "today"}}, "Destination": {"Station": {"code": "676853", "Name": "大濠公園／西鉄バス"}}, "DepartureState": {"Datetime": {"text": "08:55:00+09:00", "operation": "today"}}}, {"trainID": "53", "Name": "２７・普通・香椎参道－名島－昭和通－天神", "ArrivalState": {"Datetime": {"text": "08:57:00+09:00", "operation": "today"}}, "Destination": {"Station": {"code": "676853", "Name": "大濠公園／西鉄バス"}}, "DepartureState": {"Datetime": {"text": "08:55:00+09:00", "operation": "today"}}}, {"trainID": "54", "Name": "２・普通・西新－次郎丸", "ArrivalState": {"Datetime": {"text": "09:03:00+09:00", "operation": "today"}}, "Destination": {"Station": {"code": "675273", "Name": "四箇田団地／西鉄バス"}}, "DepartureState": {"Datetime": {"text": "09:01:00+09:00", "operation": "today"}}}, {"trainID": "55", "Name": "２７０・普通・みどりが丘－香椎参道－都高", "ArrivalState": {"Datetime": {"text": "09:03:00+09:00", "operation": "today"}}, "Destination": {"Station": {"code": "676853", "Name": "大濠公園／西鉄バス"}}, "DepartureState": {"Datetime": {"text": "09:01:00+09:00", "operation": "today"}}}, {"trainID": "56", "Name": "３２・普通・志免－亀山－空港通博多駅－昭和通天神", "ArrivalState": {"Datetime": {"text": "09:11:00+09:00", "operation": "today"}}, "Destination": {"Station": {"code": "676853", "Name": "大濠公園／西鉄バス"}}, "DepartureState": {"Datetime": {"text": "09:09:00+09:00", "operation": "today"}}}, {"trainID": "57", "Name": "２７Ｂ・普通・香椎参道－都高－昭和通－天神", "ArrivalState": {"Datetime": {"text": "09:11:00+09:00", "operation": "today"}}, "Destination": {"Station": {"code": "676853", "Name": "大濠公園／西鉄バス"}}, "DepartureState": {"Datetime": {"text": "09:09:00+09:00", "operation": "today"}}}, {"trainID": "58", "Name": "２－３・普通・西新－室住団地－橋本", "ArrivalState": {"Datetime": {"text": "09:13:00+09:00", "operation": "today"}}, "Destination": {"Station": {"code": "675435", "Name": "野方(営業所)／西鉄バス"}}, "DepartureState": {"Datetime": {"text": "09:11:00+09:00", "operation": "today"}}}, {"trainID": "59", "Name": "２７・普通・香椎参道－名島－昭和通－天神", "ArrivalState": {"Datetime": {"text": "09:14:00+09:00", "operation": "today"}}, "Destination": {"Station": {"code": "676853", "Name": "大濠公園／西鉄バス"}}, "DepartureState": {"Datetime": {"text": "09:12:00+09:00", "operation": "today"}}}, {"trainID": "60", "Name": "２３Ｎ・普通・香椎－海岸通り－名島ランプ－天神", "ArrivalState": {"Datetime": {"text": "09:18:00+09:00", "operation": "today"}}, "Destination": {"Station": {"code": "676853", "Name": "大濠公園／西鉄バス"}}, "DepartureState": {"Datetime": {"text": "09:16:00+09:00", "operation": "today"}}}, {"trainID": "61", "Name": "３４・普通・志免－亀山－妙見－昭和通－天神", "ArrivalState": {"Datetime": {"text": "09:22:00+09:00", "operation": "today"}}, "Destination": {"Station": {"code": "676853", "Name": "大濠公園／西鉄バス"}}, "DepartureState": {"Datetime": {"text": "09:20:00+09:00", "operation": "today"}}}, {"trainID": "62", "Name": "２・普通・西新－田隈新町－福歯大病院", "ArrivalState": {"Datetime": {"text": "09:25:00+09:00", "operation": "today"}}, "Destination": {"Station": {"code": "675273", "Name": "四箇田団地／西鉄バス"}}, "DepartureState": {"Datetime": {"text": "09:23:00+09:00", "operation": "today"}}}, {"trainID": "63", "Name": "２７０・普通・みどりが丘－香椎参道－都高", "ArrivalState": {"Datetime": {"text": "09:31:00+09:00", "operation": "today"}}, "Destination": {"Station": {"code": "676853", "Name": "大濠公園／西鉄バス"}}, "DepartureState": {"Datetime": {"text": "09:29:00+09:00", "operation": "today"}}}, {"trainID": "64", "Name": "２・普通・西新－次郎丸", "ArrivalState": {"Datetime": {"text": "09:33:00+09:00", "operation": "today"}}, "Destination": {"Station": {"code": "675273", "Name": "四箇田団地／西鉄バス"}}, "DepartureState": {"Datetime": {"text": "09:31:00+09:00", "operation": "today"}}}, {"trainID": "65", "Name": "２８・普通・青葉台口－香椎参道名島－昭和通－天神", "ArrivalState": {"Datetime": {"text": "09:34:00+09:00", "operation": "today"}}, "Destination": {"Station": {"code": "676853", "Name": "大濠公園／西鉄バス"}}, "DepartureState": {"Datetime": {"text": "09:32:00+09:00", "operation": "today"}}}, {"trainID": "66", "Name": "３２・普通・志免－亀山－空港通博多駅－昭和通天神", "ArrivalState": {"Datetime": {"text": "09:41:00+09:00", "operation": "today"}}, "Destination": {"Station": {"code": "676853", "Name": "大濠公園／西鉄バス"}}, "DepartureState": {"Datetime": {"text": "09:39:00+09:00", "operation": "today"}}}, {"trainID": "67", "Name": "２－３・普通・西新－室住団地－橋本", "ArrivalState": {"Datetime": {"text": "09:43:00+09:00", "operation": "today"}}, "Destination": {"Station": {"code": "675435", "Name": "野方(営業所)／西鉄バス"}}, "DepartureState": {"Datetime": {"text": "09:41:00+09:00", "operation": "today"}}}, {"trainID": "68", "Name": "２３Ｎ・普通・香椎－海岸通り－名島ランプ－天神", "ArrivalState": {"Datetime": {"text": "09:46:00+09:00", "operation": "today"}}, "Destination": {"Station": {"code": "676853", "Name": "大濠公園／西鉄バス"}}, "DepartureState": {"Datetime": {"text": "09:44:00+09:00", "operation": "today"}}}, {"trainID": "69", "Name": "３４・普通・志免－亀山－妙見－昭和通－天神", "ArrivalState": {"Datetime": {"text": "09:47:00+09:00", "operation": "today"}}, "Destination": {"Station": {"code": "676853", "Name": "大濠公園／西鉄バス"}}, "DepartureState": {"Datetime": {"text": "09:45:00+09:00", "operation": "today"}}}, {"trainID": "70", "Name": "２８Ｂ・普通・青葉台口－香椎参道－都高－天神", "ArrivalState": {"Datetime": {"text": "09:51:00+09:00", "operation": "today"}}, "Destination": {"Station": {"code": "676853", "Name": "大濠公園／西鉄バス"}}, "DepartureState": {"Datetime": {"text": "09:49:00+09:00", "operation": "today"}}}, {"trainID": "71", "Name": "２・普通・西新－次郎丸－四箇田団地", "ArrivalState": {"Datetime": {"text": "09:53:00+09:00", "operation": "today"}}, "Destination": {"Station": {"code": "675272", "Name": "金武車庫／西鉄バス"}}, "DepartureState": {"Datetime": {"text": "09:51:00+09:00", "operation": "today"}}}, {"trainID": "72", "Name": "２７・普通・香椎参道－名島－昭和通－天神", "ArrivalState": {"Datetime": {"text": "09:54:00+09:00", "operation": "today"}}, "Destination": {"Station": {"code": "676853", "Name": "大濠公園／西鉄バス"}}, "DepartureState": {"Datetime": {"text": "09:52:00+09:00", "operation": "today"}}}, {"trainID": "73", "Name": "３４・普通・志免－亀山－妙見－昭和通－天神", "ArrivalState": {"Datetime": {"text": "09:55:00+09:00", "operation": "today"}}, "Destination": {"Station": {"code": "676853", "Name": "大濠公園／西鉄バス"}}, "DepartureState": {"Datetime": {"text": "09:53:00+09:00", "operation": "today"}}}, {"trainID": "74", "Name": "２－３・普通・西新－室住団地－橋本", "ArrivalState": {"Datetime": {"text": "09:58:00+09:00", "operation": "today"}}, "Destination": {"Station": {"code": "675435", "Name": "野方(営業所)／西鉄バス"}}, "DepartureState": {"Datetime": {"text": "09:56:00+09:00", "operation": "today"}}}, {"trainID": "75", "Name": "２２Ｎ・普通・病院－南公園－名島ランプ－天神", "ArrivalState": {"Datetime": {"text": "10:01:00+09:00", "operation": "today"}}, "Destination": {"Station": {"code": "676853", "Name": "大濠公園／西鉄バス"}}, "DepartureState": {"Datetime": {"text": "09:59:00+09:00", "operation": "today"}}}, {"trainID": "76", "Name": "２・普通・西新－田隈新町－病院構内乗入", "ArrivalState": {"Datetime": {"text": "10:05:00+09:00", "operation": "today"}}, "Destination": {"Station": {"code": "678138", "Name": "歯科大病院(構内)／西鉄バス"}}, "DepartureState": {"Datetime": {"text": "10:03:00+09:00", "operation": "today"}}}, {"trainID": "77", "Name": "３２・普通・志免－亀山－空港通博多駅－昭和通天神", "ArrivalState": {"Datetime": {"text": "10:08:00+09:00", "operation": "today"}}, "Destination": {"Station": {"code": "676853", "Name": "大濠公園／西鉄バス"}}, "DepartureState": {"Datetime": {"text": "10:06:00+09:00", "operation": "today"}}}, {"trainID": "78", "Name": "２７０・普通・みどりが丘－香椎参道－都高", "ArrivalState": {"Datetime": {"text": "10:11:00+09:00", "operation": "today"}}, "Destination": {"Station": {"code": "676853", "Name": "大濠公園／西鉄バス"}}, "DepartureState": {"Datetime": {"text": "10:09:00+09:00", "operation": "today"}}}, {"trainID": "79", "Name": "２・普通・西新－次郎丸", "ArrivalState": {"Datetime": {"text": "10:13:00+09:00", "operation": "today"}}, "Destination": {"Station": {"code": "675273", "Name": "四箇田団地／西鉄バス"}}, "DepartureState": {"Datetime": {"text": "10:11:00+09:00", "operation": "today"}}}, {"trainID": "80", "Name": "２７・普通・香椎参道－名島－昭和通－天神", "ArrivalState": {"Datetime": {"text": "10:14:00+09:00", "operation": "today"}}, "Destination": {"Station": {"code": "676853", "Name": "大濠公園／西鉄バス"}}, "DepartureState": {"Datetime": {"text": "10:12:00+09:00", "operation": "today"}}}, {"trainID": "81", "Name": "２３Ｎ・普通・香椎－海岸通り－名島ランプ－天神", "ArrivalState": {"Datetime": {"text": "10:16:00+09:00", "operation": "today"}}, "Destination": {"Station": {"code": "676853", "Name": "大濠公園／西鉄バス"}}, "DepartureState": {"Datetime": {"text": "10:14:00+09:00", "operation": "today"}}}, {"trainID": "82", "Name": "２・普通・西新－田隈新町－福歯大病院", "ArrivalState": {"Datetime": {"text": "10:20:00+09:00", "operation": "today"}}, "Destination": {"Station": {"code": "675272", "Name": "金武車庫／西鉄バス"}}, "DepartureState": {"Datetime": {"text": "10:18:00+09:00", "operation": "today"}}}, {"trainID": "83", "Name": "３２・普通・志免－亀山－空港通博多駅－昭和通天神", "ArrivalState": {"Datetime": {"text": "10:21:00+09:00", "operation": "today"}}, "Destination": {"Station": {"code": "676853", "Name": "大濠公園／西鉄バス"}}, "DepartureState": {"Datetime": {"text": "10:19:00+09:00", "operation": "today"}}}, {"trainID": "84", "Name": "２・普通・西新－次郎丸", "ArrivalState": {"Datetime": {"text": "10:30:00+09:00", "operation": "today"}}, "Destination": {"Station": {"code": "675273", "Name": "四箇田団地／西鉄バス"}}, "DepartureState": {"Datetime": {"text": "10:28:00+09:00", "operation": "today"}}}, {"trainID": "85", "Name": "２７Ｂ・普通・香椎参道－都高－昭和通－天神", "ArrivalState": {"Datetime": {"text": "10:31:00+09:00", "operation": "today"}}, "Destination": {"Station": {"code": "676853", "Name": "大濠公園／西鉄バス"}}, "DepartureState": {"Datetime": {"text": "10:29:00+09:00", "operation": "today"}}}, {"trainID": "86", "Name": "２２Ｎ・普通・病院－南公園－名島ランプ－天神", "ArrivalState": {"Datetime": {"text": "10:31:00+09:00", "operation": "today"}}, "Destination": {"Station": {"code": "676853", "Name": "大濠公園／西鉄バス"}}, "DepartureState": {"Datetime": {"text": "10:29:00+09:00", "operation": "today"}}}, {"trainID": "87", "Name": "２８・普通・青葉台口－香椎参道名島－昭和通－天神", "ArrivalState": {"Datetime": {"text": "10:34:00+09:00", "operation": "today"}}, "Destination": {"Station": {"code": "676853", "Name": "大濠公園／西鉄バス"}}, "DepartureState": {"Datetime": {"text": "10:32:00+09:00", "operation": "today"}}}, {"trainID": "88", "Name": "２－３・普通・西新－室住団地－橋本", "ArrivalState": {"Datetime": {"text": "10:41:00+09:00", "operation": "today"}}, "Destination": {"Station": {"code": "675435", "Name": "野方(営業所)／西鉄バス"}}, "DepartureState": {"Datetime": {"text": "10:39:00+09:00", "operation": "today"}}}, {"trainID": "89", "Name": "３２・普通・志免－亀山－空港通博多駅－昭和通天神", "ArrivalState": {"Datetime": {"text": "10:46:00+09:00", "operation": "today"}}, "Destination": {"Station": {"code": "676853", "Name": "大濠公園／西鉄バス"}}, "DepartureState": {"Datetime": {"text": "10:44:00+09:00", "operation": "today"}}}, {"trainID": "90", "Name": "２３Ｎ・普通・香椎－海岸通り－名島ランプ－天神", "ArrivalState": {"Datetime": {"text": "10:46:00+09:00", "operation": "today"}}, "Destination": {"Station": {"code": "676853", "Name": "大濠公園／西鉄バス"}}, "DepartureState": {"Datetime": {"text": "10:44:00+09:00", "operation": "today"}}}, {"trainID": "91", "Name": "２８Ｂ・普通・青葉台口－香椎参道－都高－天神", "ArrivalState": {"Datetime": {"text": "10:51:00+09:00", "operation": "today"}}, "Destination": {"Station": {"code": "676853", "Name": "大濠公園／西鉄バス"}}, "DepartureState": {"Datetime": {"text": "10:49:00+09:00", "operation": "today"}}}, {"trainID": "92", "Name": "３４・普通・志免－亀山－妙見－昭和通－天神", "ArrivalState": {"Datetime": {"text": "10:51:00+09:00", "operation": "today"}}, "Destination": {"Station": {"code": "676853", "Name": "大濠公園／西鉄バス"}}, "DepartureState": {"Datetime": {"text": "10:49:00+09:00", "operation": "today"}}}, {"trainID": "93", "Name": "２７・普通・香椎参道－名島－昭和通－天神", "ArrivalState": {"Datetime": {"text": "10:54:00+09:00", "operation": "today"}}, "Destination": {"Station": {"code": "676853", "Name": "大濠公園／西鉄バス"}}, "DepartureState": {"Datetime": {"text": "10:52:00+09:00", "operation": "today"}}}, {"trainID": "94", "Name": "２・普通・西新－田隈新町－福歯大病院", "ArrivalState": {"Datetime": {"text": "10:56:00+09:00", "operation": "today"}}, "Destination": {"Station": {"code": "675272", "Name": "金武車庫／西鉄バス"}}, "DepartureState": {"Datetime": {"text": "10:54:00+09:00", "operation": "today"}}}, {"trainID": "95", "Name": "２２Ｎ・普通・病院－南公園－名島ランプ－天神", "ArrivalState": {"Datetime": {"text": "11:01:00+09:00", "operation": "today"}}, "Destination": {"Station": {"code": "676853", "Name": "大濠公園／西鉄バス"}}, "DepartureState": {"Datetime": {"text": "10:59:00+09:00", "operation": "today"}}}, {"trainID": "96", "Name": "２・普通・西新－次郎丸", "ArrivalState": {"Datetime": {"text": "11:04:00+09:00", "operation": "today"}}, "Destination": {"Station": {"code": "675273", "Name": "四箇田団地／西鉄バス"}}, "DepartureState": {"Datetime": {"text": "11:02:00+09:00", "operation": "today"}}}, {"trainID": "97", "Name": "３０・普通・亀山－空港通－博多駅－昭和通天神", "ArrivalState": {"Datetime": {"text": "11:06:00+09:00", "operation": "today"}}, "Destination": {"Station": {"code": "676853", "Name": "大濠公園／西鉄バス"}}, "DepartureState": {"Datetime": {"text": "11:04:00+09:00", "operation": "today"}}}, {"trainID": "98", "Name": "２７０・普通・みどりが丘－香椎参道－都高", "ArrivalState": {"Datetime": {"text": "11:11:00+09:00", "operation": "today"}}, "Destination": {"Station": {"code": "676853", "Name": "大濠公園／西鉄バス"}}, "DepartureState": {"Datetime": {"text": "11:09:00+09:00", "operation": "today"}}}, {"trainID": "99", "Name": "２７・普通・香椎参道－名島－昭和通－天神", "ArrivalState": {"Datetime": {"text": "11:14:00+09:00", "operation": "today"}}, "Destination": {"Station": {"code": "676853", "Name": "大濠公園／西鉄バス"}}, "DepartureState": {"Datetime": {"text": "11:12:00+09:00", "operation": "today"}}}, {"trainID": "100", "Name": "２－３・普通・西新", "ArrivalState": {"Datetime": {"text": "11:15:00+09:00", "operation": "today"}}, "Destination": {"Station": {"code": "675471", "Name": "室住団地／西鉄バス"}}, "DepartureState": {"Datetime": {"text": "11:13:00+09:00", "operation": "today"}}}, {"trainID": "101", "Name": "２３Ｎ・普通・香椎－海岸通り－名島ランプ－天神", "ArrivalState": {"Datetime": {"text": "11:16:00+09:00", "operation": "today"}}, "Destination": {"Station": {"code": "676853", "Name": "大濠公園／西鉄バス"}}, "DepartureState": {"Datetime": {"text": "11:14:00+09:00", "operation": "today"}}}, {"trainID": "102", "Name": "３４・普通・志免－亀山－妙見－昭和通－天神", "ArrivalState": {"Datetime": {"text": "11:21:00+09:00", "operation": "today"}}, "Destination": {"Station": {"code": "676853", "Name": "大濠公園／西鉄バス"}}, "DepartureState": {"Datetime": {"text": "11:19:00+09:00", "operation": "today"}}}, {"trainID": "103", "Name": "２・普通・西新－次郎丸－四箇田団地", "ArrivalState": {"Datetime": {"text": "11:25:00+09:00", "operation": "today"}}, "Destination": {"Station": {"code": "675272", "Name": "金武車庫／西鉄バス"}}, "DepartureState": {"Datetime": {"text": "11:23:00+09:00", "operation": "today"}}}, {"trainID": "104", "Name": "２７Ｂ・普通・香椎参道－都高－昭和通－天神", "ArrivalState": {"Datetime": {"text": "11:31:00+09:00", "operation": "today"}}, "Destination": {"Station": {"code": "676853", "Name": "大濠公園／西鉄バス"}}, "DepartureState": {"Datetime": {"text": "11:29:00+09:00", "operation": "today"}}}, {"trainID": "105", "Name": "２２Ｎ・普通・病院－南公園－名島ランプ－天神", "ArrivalState": {"Datetime": {"text": "11:31:00+09:00", "operation": "today"}}, "Destination": {"Station": {"code": "676853", "Name": "大濠公園／西鉄バス"}}, "DepartureState": {"Datetime": {"text": "11:29:00+09:00", "operation": "today"}}}, {"trainID": "106", "Name": "２８・普通・青葉台口－香椎参道名島－昭和通－天神", "ArrivalState": {"Datetime": {"text": "11:34:00+09:00", "operation": "today"}}, "Destination": {"Station": {"code": "676853", "Name": "大濠公園／西鉄バス"}}, "DepartureState": {"Datetime": {"text": "11:32:00+09:00", "operation": "today"}}}, {"trainID": "107", "Name": "３０・普通・亀山－空港通－博多駅－昭和通天神", "ArrivalState": {"Datetime": {"text": "11:36:00+09:00", "operation": "today"}}, "Destination": {"Station": {"code": "676853", "Name": "大濠公園／西鉄バス"}}, "DepartureState": {"Datetime": {"text": "11:34:00+09:00", "operation": "today"}}}, {"trainID": "108", "Name": "２－３・普通・西新－室住団地－橋本", "ArrivalState": {"Datetime": {"text": "11:39:00+09:00", "operation": "today"}}, "Destination": {"Station": {"code": "675435", "Name": "野方(営業所)／西鉄バス"}}, "DepartureState": {"Datetime": {"text": "11:37:00+09:00", "operation": "today"}}}, {"trainID": "109", "Name": "２３Ｎ・普通・香椎－海岸通り－名島ランプ－天神", "ArrivalState": {"Datetime": {"text": "11:46:00+09:00", "operation": "today"}}, "Destination": {"Station": {"code": "676853", "Name": "大濠公園／西鉄バス"}}, "DepartureState": {"Datetime": {"text": "11:44:00+09:00", "operation": "today"}}}, {"trainID": "110", "Name": "２８Ｂ・普通・青葉台口－香椎参道－都高－天神", "ArrivalState": {"Datetime": {"text": "11:51:00+09:00", "operation": "today"}}, "Destination": {"Station": {"code": "676853", "Name": "大濠公園／西鉄バス"}}, "DepartureState": {"Datetime": {"text": "11:49:00+09:00", "operation": "today"}}}, {"trainID": "111", "Name": "３４・普通・志免－亀山－妙見－昭和通－天神", "ArrivalState": {"Datetime": {"text": "11:51:00+09:00", "operation": "today"}}, "Destination": {"Station": {"code": "676853", "Name": "大濠公園／西鉄バス"}}, "DepartureState": {"Datetime": {"text": "11:49:00+09:00", "operation": "today"}}}, {"trainID": "112", "Name": "２・普通・西新－田隈新町－福歯大病院", "ArrivalState": {"Datetime": {"text": "11:53:00+09:00", "operation": "today"}}, "Destination": {"Station": {"code": "675273", "Name": "四箇田団地／西鉄バス"}}, "DepartureState": {"Datetime": {"text": "11:51:00+09:00", "operation": "today"}}}, {"trainID": "113", "Name": "２７・普通・香椎参道－名島－昭和通－天神", "ArrivalState": {"Datetime": {"text": "11:54:00+09:00", "operation": "today"}}, "Destination": {"Station": {"code": "676853", "Name": "大濠公園／西鉄バス"}}, "DepartureState": {"Datetime": {"text": "11:52:00+09:00", "operation": "today"}}}, {"trainID": "114", "Name": "２２Ｎ・普通・病院－南公園－名島ランプ－天神", "ArrivalState": {"Datetime": {"text": "12:01:00+09:00", "operation": "today"}}, "Destination": {"Station": {"code": "676853", "Name": "大濠公園／西鉄バス"}}, "DepartureState": {"Datetime": {"text": "11:59:00+09:00", "operation": "today"}}}, {"trainID": "115", "Name": "２－３・普通・西新－室住団地－橋本", "ArrivalState": {"Datetime": {"text": "12:10:00+09:00", "operation": "today"}}, "Destination": {"Station": {"code": "675435", "Name": "野方(営業所)／西鉄バス"}}, "DepartureState": {"Datetime": {"text": "12:08:00+09:00", "operation": "today"}}}, {"trainID": "116", "Name": "３２・普通・志免－亀山－空港通博多駅－昭和通天神", "ArrivalState": {"Datetime": {"text": "12:11:00+09:00", "operation": "today"}}, "Destination": {"Station": {"code": "676853", "Name": "大濠公園／西鉄バス"}}, "DepartureState": {"Datetime": {"text": "12:09:00+09:00", "operation": "today"}}}, {"trainID": "117", "Name": "２７０・普通・みどりが丘－香椎参道－都高", "ArrivalState": {"Datetime": {"text": "12:11:00+09:00", "operation": "today"}}, "Destination": {"Station": {"code": "676853", "Name": "大濠公園／西鉄バス"}}, "DepartureState": {"Datetime": {"text": "12:09:00+09:00", "operation": "today"}}}, {"trainID": "118", "Name": "２７・普通・香椎参道－名島－昭和通－天神", "ArrivalState": {"Datetime": {"text": "12:14:00+09:00", "operation": "today"}}, "Destination": {"Station": {"code": "676853", "Name": "大濠公園／西鉄バス"}}, "DepartureState": {"Datetime": {"text": "12:12:00+09:00", "operation": "today"}}}, {"trainID": "119", "Name": "２３Ｎ・普通・香椎－海岸通り－名島ランプ－天神", "ArrivalState": {"Datetime": {"text": "12:16:00+09:00", "operation": "today"}}, "Destination": {"Station": {"code": "676853", "Name": "大濠公園／西鉄バス"}}, "DepartureState": {"Datetime": {"text": "12:14:00+09:00", "operation": "today"}}}, {"trainID": "120", "Name": "３４・普通・志免－亀山－妙見－昭和通－天神", "ArrivalState": {"Datetime": {"text": "12:21:00+09:00", "operation": "today"}}, "Destination": {"Station": {"code": "676853", "Name": "大濠公園／西鉄バス"}}, "DepartureState": {"Datetime": {"text": "12:19:00+09:00", "operation": "today"}}}, {"trainID": "121", "Name": "２・普通・西新－次郎丸", "ArrivalState": {"Datetime": {"text": "12:25:00+09:00", "operation": "today"}}, "Destination": {"Station": {"code": "675273", "Name": "四箇田団地／西鉄バス"}}, "DepartureState": {"Datetime": {"text": "12:23:00+09:00", "operation": "today"}}}, {"trainID": "122", "Name": "２７Ｂ・普通・香椎参道－都高－昭和通－天神", "ArrivalState": {"Datetime": {"text": "12:31:00+09:00", "operation": "today"}}, "Destination": {"Station": {"code": "676853", "Name": "大濠公園／西鉄バス"}}, "DepartureState": {"Datetime": {"text": "12:29:00+09:00", "operation": "today"}}}, {"trainID": "123", "Name": "２２Ｎ・普通・病院－南公園－名島ランプ－天神", "ArrivalState": {"Datetime": {"text": "12:31:00+09:00", "operation": "today"}}, "Destination": {"Station": {"code": "676853", "Name": "大濠公園／西鉄バス"}}, "DepartureState": {"Datetime": {"text": "12:29:00+09:00", "operation": "today"}}}, {"trainID": "124", "Name": "２８・普通・青葉台口－香椎参道名島－昭和通－天神", "ArrivalState": {"Datetime": {"text": "12:34:00+09:00", "operation": "today"}}, "Destination": {"Station": {"code": "676853", "Name": "大濠公園／西鉄バス"}}, "DepartureState": {"Datetime": {"text": "12:32:00+09:00", "operation": "today"}}}, {"trainID": "125", "Name": "２－３・普通・西新－室住団地－橋本", "ArrivalState": {"Datetime": {"text": "12:36:00+09:00", "operation": "today"}}, "Destination": {"Station": {"code": "675435", "Name": "野方(営業所)／西鉄バス"}}, "DepartureState": {"Datetime": {"text": "12:34:00+09:00", "operation": "today"}}}, {"trainID": "126", "Name": "３２・普通・志免－亀山－空港通博多駅－昭和通天神", "ArrivalState": {"Datetime": {"text": "12:36:00+09:00", "operation": "today"}}, "Destination": {"Station": {"code": "676853", "Name": "大濠公園／西鉄バス"}}, "DepartureState": {"Datetime": {"text": "12:34:00+09:00", "operation": "today"}}}, {"trainID": "127", "Name": "２３Ｎ・普通・香椎－海岸通り－名島ランプ－天神", "ArrivalState": {"Datetime": {"text": "12:46:00+09:00", "operation": "today"}}, "Destination": {"Station": {"code": "676853", "Name": "大濠公園／西鉄バス"}}, "DepartureState": {"Datetime": {"text": "12:44:00+09:00", "operation": "today"}}}, {"trainID": "128", "Name": "２・普通・西新－田隈新町－福歯大病院", "ArrivalState": {"Datetime": {"text": "12:48:00+09:00", "operation": "today"}}, "Destination": {"Station": {"code": "675273", "Name": "四箇田団地／西鉄バス"}}, "DepartureState": {"Datetime": {"text": "12:46:00+09:00", "operation": "today"}}}, {"trainID": "129", "Name": "２８Ｂ・普通・青葉台口－香椎参道－都高－天神", "ArrivalState": {"Datetime": {"text": "12:51:00+09:00", "operation": "today"}}, "Destination": {"Station": {"code": "676853", "Name": "大濠公園／西鉄バス"}}, "DepartureState": {"Datetime": {"text": "12:49:00+09:00", "operation": "today"}}}, {"trainID": "130", "Name": "３４・普通・志免－亀山－妙見－昭和通－天神", "ArrivalState": {"Datetime": {"text": "12:51:00+09:00", "operation": "today"}}, "Destination": {"Station": {"code": "676853", "Name": "大濠公園／西鉄バス"}}, "DepartureState": {"Datetime": {"text": "12:49:00+09:00", "operation": "today"}}}, {"trainID": "131", "Name": "２７・普通・香椎参道－名島－昭和通－天神", "ArrivalState": {"Datetime": {"text": "12:54:00+09:00", "operation": "today"}}, "Destination": {"Station": {"code": "676853", "Name": "大濠公園／西鉄バス"}}, "DepartureState": {"Datetime": {"text": "12:52:00+09:00", "operation": "today"}}}, {"trainID": "132", "Name": "２２Ｎ・普通・病院－南公園－名島ランプ－天神", "ArrivalState": {"Datetime": {"text": "13:01:00+09:00", "operation": "today"}}, "Destination": {"Station": {"code": "676853", "Name": "大濠公園／西鉄バス"}}, "DepartureState": {"Datetime": {"text": "12:59:00+09:00", "operation": "today"}}}, {"trainID": "133", "Name": "２－３・普通・西新－室住団地－橋本", "ArrivalState": {"Datetime": {"text": "13:03:00+09:00", "operation": "today"}}, "Destination": {"Station": {"code": "675435", "Name": "野方(営業所)／西鉄バス"}}, "DepartureState": {"Datetime": {"text": "13:01:00+09:00", "operation": "today"}}}, {"trainID": "134", "Name": "３０・普通・亀山－空港通－博多駅－昭和通天神", "ArrivalState": {"Datetime": {"text": "13:05:00+09:00", "operation": "today"}}, "Destination": {"Station": {"code": "676853", "Name": "大濠公園／西鉄バス"}}, "DepartureState": {"Datetime": {"text": "13:03:00+09:00", "operation": "today"}}}, {"trainID": "135", "Name": "２７０・普通・みどりが丘－香椎参道－都高", "ArrivalState": {"Datetime": {"text": "13:11:00+09:00", "operation": "today"}}, "Destination": {"Station": {"code": "676853", "Name": "大濠公園／西鉄バス"}}, "DepartureState": {"Datetime": {"text": "13:09:00+09:00", "operation": "today"}}}, {"trainID": "136", "Name": "２７・普通・香椎参道－名島－昭和通－天神", "ArrivalState": {"Datetime": {"text": "13:14:00+09:00", "operation": "today"}}, "Destination": {"Station": {"code": "676853", "Name": "大濠公園／西鉄バス"}}, "DepartureState": {"Datetime": {"text": "13:12:00+09:00", "operation": "today"}}}, {"trainID": "137", "Name": "２・普通・西新－次郎丸", "ArrivalState": {"Datetime": {"text": "13:15:00+09:00", "operation": "today"}}, "Destination": {"Station": {"code": "675273", "Name": "四箇田団地／西鉄バス"}}, "DepartureState": {"Datetime": {"text": "13:13:00+09:00", "operation": "today"}}}, {"trainID": "138", "Name": "２３Ｎ・普通・香椎－海岸通り－名島ランプ－天神", "ArrivalState": {"Datetime": {"text": "13:16:00+09:00", "operation": "today"}}, "Destination": {"Station": {"code": "676853", "Name": "大濠公園／西鉄バス"}}, "DepartureState": {"Datetime": {"text": "13:14:00+09:00", "operation": "today"}}}, {"trainID": "139", "Name": "３４・普通・志免－亀山－妙見－昭和通－天神", "ArrivalState": {"Datetime": {"text": "13:21:00+09:00", "operation": "today"}}, "Destination": {"Station": {"code": "676853", "Name": "大濠公園／西鉄バス"}}, "DepartureState": {"Datetime": {"text": "13:19:00+09:00", "operation": "today"}}}, {"trainID": "140", "Name": "２・普通・西新－田隈新町－福歯大病院", "ArrivalState": {"Datetime": {"text": "13:31:00+09:00", "operation": "today"}}, "Destination": {"Station": {"code": "675273", "Name": "四箇田団地／西鉄バス"}}, "DepartureState": {"Datetime": {"text": "13:29:00+09:00", "operation": "today"}}}, {"trainID": "141", "Name": "２７Ｂ・普通・香椎参道－都高－昭和通－天神", "ArrivalState": {"Datetime": {"text": "13:31:00+09:00", "operation": "today"}}, "Destination": {"Station": {"code": "676853", "Name": "大濠公園／西鉄バス"}}, "DepartureState": {"Datetime": {"text": "13:29:00+09:00", "operation": "today"}}}, {"trainID": "142", "Name": "２２Ｎ・普通・病院－南公園－名島ランプ－天神", "ArrivalState": {"Datetime": {"text": "13:31:00+09:00", "operation": "today"}}, "Destination": {"Station": {"code": "676853", "Name": "大濠公園／西鉄バス"}}, "DepartureState": {"Datetime": {"text": "13:29:00+09:00", "operation": "today"}}}, {"trainID": "143", "Name": "２８・普通・青葉台口－香椎参道名島－昭和通－天神", "ArrivalState": {"Datetime": {"text": "13:34:00+09:00", "operation": "today"}}, "Destination": {"Station": {"code": "676853", "Name": "大濠公園／西鉄バス"}}, "DepartureState": {"Datetime": {"text": "13:32:00+09:00", "operation": "today"}}}, {"trainID": "144", "Name": "３２・普通・志免－亀山－空港通博多駅－昭和通天神", "ArrivalState": {"Datetime": {"text": "13:36:00+09:00", "operation": "today"}}, "Destination": {"Station": {"code": "676853", "Name": "大濠公園／西鉄バス"}}, "DepartureState": {"Datetime": {"text": "13:34:00+09:00", "operation": "today"}}}, {"trainID": "145", "Name": "２－３・普通・西新", "ArrivalState": {"Datetime": {"text": "13:43:00+09:00", "operation": "today"}}, "Destination": {"Station": {"code": "675471", "Name": "室住団地／西鉄バス"}}, "DepartureState": {"Datetime": {"text": "13:41:00+09:00", "operation": "today"}}}, {"trainID": "146", "Name": "２３Ｎ・普通・香椎－海岸通り－名島ランプ－天神", "ArrivalState": {"Datetime": {"text": "13:46:00+09:00", "operation": "today"}}, "Destination": {"Station": {"code": "676853", "Name": "大濠公園／西鉄バス"}}, "DepartureState": {"Datetime": {"text": "13:44:00+09:00", "operation": "today"}}}, {"trainID": "147", "Name": "２８Ｂ・普通・青葉台口－香椎参道－都高－天神", "ArrivalState": {"Datetime": {"text": "13:51:00+09:00", "operation": "today"}}, "Destination": {"Station": {"code": "676853", "Name": "大濠公園／西鉄バス"}}, "DepartureState": {"Datetime": {"text": "13:49:00+09:00", "operation": "today"}}}, {"trainID": "148", "Name": "３４・普通・志免－亀山－妙見－昭和通－天神", "ArrivalState": {"Datetime": {"text": "13:51:00+09:00", "operation": "today"}}, "Destination": {"Station": {"code": "676853", "Name": "大濠公園／西鉄バス"}}, "DepartureState": {"Datetime": {"text": "13:49:00+09:00", "operation": "today"}}}, {"trainID": "149", "Name": "２７・普通・香椎参道－名島－昭和通－天神", "ArrivalState": {"Datetime": {"text": "13:54:00+09:00", "operation": "today"}}, "Destination": {"Station": {"code": "676853", "Name": "大濠公園／西鉄バス"}}, "DepartureState": {"Datetime": {"text": "13:52:00+09:00", "operation": "today"}}}, {"trainID": "150", "Name": "２・普通・西新－田隈新町－福歯大病院", "ArrivalState": {"Datetime": {"text": "13:55:00+09:00", "operation": "today"}}, "Destination": {"Station": {"code": "675273", "Name": "四箇田団地／西鉄バス"}}, "DepartureState": {"Datetime": {"text": "13:53:00+09:00", "operation": "today"}}}, {"trainID": "151", "Name": "２２Ｎ・普通・病院－南公園－名島ランプ－天神", "ArrivalState": {"Datetime": {"text": "14:01:00+09:00", "operation": "today"}}, "Destination": {"Station": {"code": "676853", "Name": "大濠公園／西鉄バス"}}, "DepartureState": {"Datetime": {"text": "13:59:00+09:00", "operation": "today"}}}, {"trainID": "152", "Name": "３２・普通・志免－亀山－空港通博多駅－昭和通天神", "ArrivalState": {"Datetime": {"text": "14:11:00+09:00", "operation": "today"}}, "Destination": {"Station": {"code": "676853", "Name": "大濠公園／西鉄バス"}}, "DepartureState": {"Datetime": {"text": "14:09:00+09:00", "operation": "today"}}}, {"trainID": "153", "Name": "２７０・普通・みどりが丘－香椎参道－都高", "ArrivalState": {"Datetime": {"text": "14:11:00+09:00", "operation": "today"}}, "Destination": {"Station": {"code": "676853", "Name": "大濠公園／西鉄バス"}}, "DepartureState": {"Datetime": {"text": "14:09:00+09:00", "operation": "today"}}}, {"trainID": "154", "Name": "２－３・普通・西新－室住団地－橋本", "ArrivalState": {"Datetime": {"text": "14:12:00+09:00", "operation": "today"}}, "Destination": {"Station": {"code": "675435", "Name": "野方(営業所)／西鉄バス"}}, "DepartureState": {"Datetime": {"text": "14:10:00+09:00", "operation": "today"}}}, {"trainID": "155", "Name": "２７・普通・香椎参道－名島－昭和通－天神", "ArrivalState": {"Datetime": {"text": "14:14:00+09:00", "operation": "today"}}, "Destination": {"Station": {"code": "676853", "Name": "大濠公園／西鉄バス"}}, "DepartureState": {"Datetime": {"text": "14:12:00+09:00", "operation": "today"}}}, {"trainID": "156", "Name": "２３Ｎ・普通・香椎－海岸通り－名島ランプ－天神", "ArrivalState": {"Datetime": {"text": "14:16:00+09:00", "operation": "today"}}, "Destination": {"Station": {"code": "676853", "Name": "大濠公園／西鉄バス"}}, "DepartureState": {"Datetime": {"text": "14:14:00+09:00", "operation": "today"}}}, {"trainID": "157", "Name": "３４・普通・志免－亀山－妙見－昭和通－天神", "ArrivalState": {"Datetime": {"text": "14:21:00+09:00", "operation": "today"}}, "Destination": {"Station": {"code": "676853", "Name": "大濠公園／西鉄バス"}}, "DepartureState": {"Datetime": {"text": "14:19:00+09:00", "operation": "today"}}}, {"trainID": "158", "Name": "２・普通・西新－次郎丸", "ArrivalState": {"Datetime": {"text": "14:23:00+09:00", "operation": "today"}}, "Destination": {"Station": {"code": "675273", "Name": "四箇田団地／西鉄バス"}}, "DepartureState": {"Datetime": {"text": "14:21:00+09:00", "operation": "today"}}}, {"trainID": "159", "Name": "２７Ｂ・普通・香椎参道－都高－昭和通－天神", "ArrivalState": {"Datetime": {"text": "14:31:00+09:00", "operation": "today"}}, "Destination": {"Station": {"code": "676853", "Name": "大濠公園／西鉄バス"}}, "DepartureState": {"Datetime": {"text": "14:29:00+09:00", "operation": "today"}}}, {"trainID": "160", "Name": "２２Ｎ・普通・病院－南公園－名島ランプ－天神", "ArrivalState": {"Datetime": {"text": "14:31:00+09:00", "operation": "today"}}, "Destination": {"Station": {"code": "676853", "Name": "大濠公園／西鉄バス"}}, "DepartureState": {"Datetime": {"text": "14:29:00+09:00", "operation": "today"}}}, {"trainID": "161", "Name": "２－３・普通・西新－室住団地－橋本", "ArrivalState": {"Datetime": {"text": "14:33:00+09:00", "operation": "today"}}, "Destination": {"Station": {"code": "675435", "Name": "野方(営業所)／西鉄バス"}}, "DepartureState": {"Datetime": {"text": "14:31:00+09:00", "operation": "today"}}}, {"trainID": "162", "Name": "２８・普通・青葉台口－香椎参道名島－昭和通－天神", "ArrivalState": {"Datetime": {"text": "14:34:00+09:00", "operation": "today"}}, "Destination": {"Station": {"code": "676853", "Name": "大濠公園／西鉄バス"}}, "DepartureState": {"Datetime": {"text": "14:32:00+09:00", "operation": "today"}}}, {"trainID": "163", "Name": "３０・普通・亀山－空港通－博多駅－昭和通天神", "ArrivalState": {"Datetime": {"text": "14:36:00+09:00", "operation": "today"}}, "Destination": {"Station": {"code": "676853", "Name": "大濠公園／西鉄バス"}}, "DepartureState": {"Datetime": {"text": "14:34:00+09:00", "operation": "today"}}}, {"trainID": "164", "Name": "２３Ｎ・普通・香椎－海岸通り－名島ランプ－天神", "ArrivalState": {"Datetime": {"text": "14:46:00+09:00", "operation": "today"}}, "Destination": {"Station": {"code": "676853", "Name": "大濠公園／西鉄バス"}}, "DepartureState": {"Datetime": {"text": "14:44:00+09:00", "operation": "today"}}}, {"trainID": "165", "Name": "２・普通・西新－田隈新町－福歯大病院", "ArrivalState": {"Datetime": {"text": "14:50:00+09:00", "operation": "today"}}, "Destination": {"Station": {"code": "675272", "Name": "金武車庫／西鉄バス"}}, "DepartureState": {"Datetime": {"text": "14:48:00+09:00", "operation": "today"}}}, {"trainID": "166", "Name": "２８Ｂ・普通・青葉台口－香椎参道－都高－天神", "ArrivalState": {"Datetime": {"text": "14:51:00+09:00", "operation": "today"}}, "Destination": {"Station": {"code": "676853", "Name": "大濠公園／西鉄バス"}}, "DepartureState": {"Datetime": {"text": "14:49:00+09:00", "operation": "today"}}}, {"trainID": "167", "Name": "３４・普通・志免－亀山－妙見－昭和通－天神", "ArrivalState": {"Datetime": {"text": "14:51:00+09:00", "operation": "today"}}, "Destination": {"Station": {"code": "676853", "Name": "大濠公園／西鉄バス"}}, "DepartureState": {"Datetime": {"text": "14:49:00+09:00", "operation": "today"}}}, {"trainID": "168", "Name": "２７・普通・香椎参道－名島－昭和通－天神", "ArrivalState": {"Datetime": {"text": "14:54:00+09:00", "operation": "today"}}, "Destination": {"Station": {"code": "676853", "Name": "大濠公園／西鉄バス"}}, "DepartureState": {"Datetime": {"text": "14:52:00+09:00", "operation": "today"}}}, {"trainID": "169", "Name": "２２Ｎ・普通・病院－南公園－名島ランプ－天神", "ArrivalState": {"Datetime": {"text": "15:01:00+09:00", "operation": "today"}}, "Destination": {"Station": {"code": "676853", "Name": "大濠公園／西鉄バス"}}, "DepartureState": {"Datetime": {"text": "14:59:00+09:00", "operation": "today"}}}, {"trainID": "170", "Name": "２－３・普通・西新", "ArrivalState": {"Datetime": {"text": "15:05:00+09:00", "operation": "today"}}, "Destination": {"Station": {"code": "675471", "Name": "室住団地／西鉄バス"}}, "DepartureState": {"Datetime": {"text": "15:03:00+09:00", "operation": "today"}}}, {"trainID": "171", "Name": "３２・普通・志免－亀山－空港通博多駅－昭和通天神", "ArrivalState": {"Datetime": {"text": "15:11:00+09:00", "operation": "today"}}, "Destination": {"Station": {"code": "676853", "Name": "大濠公園／西鉄バス"}}, "DepartureState": {"Datetime": {"text": "15:09:00+09:00", "operation": "today"}}}, {"trainID": "172", "Name": "２７０・普通・みどりが丘－香椎参道－都高", "ArrivalState": {"Datetime": {"text": "15:11:00+09:00", "operation": "today"}}, "Destination": {"Station": {"code": "676853", "Name": "大濠公園／西鉄バス"}}, "DepartureState": {"Datetime": {"text": "15:09:00+09:00", "operation": "today"}}}, {"trainID": "173", "Name": "２７・普通・香椎参道－名島－昭和通－天神", "ArrivalState": {"Datetime": {"text": "15:14:00+09:00", "operation": "today"}}, "Destination": {"Station": {"code": "676853", "Name": "大濠公園／西鉄バス"}}, "DepartureState": {"Datetime": {"text": "15:12:00+09:00", "operation": "today"}}}, {"trainID": "174", "Name": "２・普通・西新－次郎丸", "ArrivalState": {"Datetime": {"text": "15:16:00+09:00", "operation": "today"}}, "Destination": {"Station": {"code": "675273", "Name": "四箇田団地／西鉄バス"}}, "DepartureState": {"Datetime": {"text": "15:14:00+09:00", "operation": "today"}}}, {"trainID": "175", "Name": "２３Ｎ・普通・香椎－海岸通り－名島ランプ－天神", "ArrivalState": {"Datetime": {"text": "15:16:00+09:00", "operation": "today"}}, "Destination": {"Station": {"code": "676853", "Name": "大濠公園／西鉄バス"}}, "DepartureState": {"Datetime": {"text": "15:14:00+09:00", "operation": "today"}}}, {"trainID": "176", "Name": "３４・普通・志免－亀山－妙見－昭和通－天神", "ArrivalState": {"Datetime": {"text": "15:21:00+09:00", "operation": "today"}}, "Destination": {"Station": {"code": "676853", "Name": "大濠公園／西鉄バス"}}, "DepartureState": {"Datetime": {"text": "15:19:00+09:00", "operation": "today"}}}, {"trainID": "177", "Name": "２７Ｂ・普通・香椎参道－都高－昭和通－天神", "ArrivalState": {"Datetime": {"text": "15:31:00+09:00", "operation": "today"}}, "Destination": {"Station": {"code": "676853", "Name": "大濠公園／西鉄バス"}}, "DepartureState": {"Datetime": {"text": "15:29:00+09:00", "operation": "today"}}}, {"trainID": "178", "Name": "２２Ｎ・普通・病院－南公園－名島ランプ－天神", "ArrivalState": {"Datetime": {"text": "15:31:00+09:00", "operation": "today"}}, "Destination": {"Station": {"code": "676853", "Name": "大濠公園／西鉄バス"}}, "DepartureState": {"Datetime": {"text": "15:29:00+09:00", "operation": "today"}}}, {"trainID": "179", "Name": "２－３・普通・西新－室住団地－橋本", "ArrivalState": {"Datetime": {"text": "15:33:00+09:00", "operation": "today"}}, "Destination": {"Station": {"code": "675435", "Name": "野方(営業所)／西鉄バス"}}, "DepartureState": {"Datetime": {"text": "15:31:00+09:00", "operation": "today"}}}, {"trainID": "180", "Name": "２８・普通・青葉台口－香椎参道名島－昭和通－天神", "ArrivalState": {"Datetime": {"text": "15:34:00+09:00", "operation": "today"}}, "Destination": {"Station": {"code": "676853", "Name": "大濠公園／西鉄バス"}}, "DepartureState": {"Datetime": {"text": "15:32:00+09:00", "operation": "today"}}}, {"trainID": "181", "Name": "３０・普通・亀山－空港通－博多駅－昭和通天神", "ArrivalState": {"Datetime": {"text": "15:36:00+09:00", "operation": "today"}}, "Destination": {"Station": {"code": "676853", "Name": "大濠公園／西鉄バス"}}, "DepartureState": {"Datetime": {"text": "15:34:00+09:00", "operation": "today"}}}, {"trainID": "182", "Name": "２３Ｎ・普通・香椎－海岸通り－名島ランプ－天神", "ArrivalState": {"Datetime": {"text": "15:46:00+09:00", "operation": "today"}}, "Destination": {"Station": {"code": "676853", "Name": "大濠公園／西鉄バス"}}, "DepartureState": {"Datetime": {"text": "15:44:00+09:00", "operation": "today"}}}, {"trainID": "183", "Name": "２・普通・西新－田隈新町－福歯大病院", "ArrivalState": {"Datetime": {"text": "15:47:00+09:00", "operation": "today"}}, "Destination": {"Station": {"code": "675273", "Name": "四箇田団地／西鉄バス"}}, "DepartureState": {"Datetime": {"text": "15:45:00+09:00", "operation": "today"}}}, {"trainID": "184", "Name": "２８Ｂ・普通・青葉台口－香椎参道－都高－天神", "ArrivalState": {"Datetime": {"text": "15:51:00+09:00", "operation": "today"}}, "Destination": {"Station": {"code": "676853", "Name": "大濠公園／西鉄バス"}}, "DepartureState": {"Datetime": {"text": "15:49:00+09:00", "operation": "today"}}}, {"trainID": "185", "Name": "３４・普通・志免－亀山－妙見－昭和通－天神", "ArrivalState": {"Datetime": {"text": "15:51:00+09:00", "operation": "today"}}, "Destination": {"Station": {"code": "676853", "Name": "大濠公園／西鉄バス"}}, "DepartureState": {"Datetime": {"text": "15:49:00+09:00", "operation": "today"}}}, {"trainID": "186", "Name": "２７・普通・香椎参道－名島－昭和通－天神", "ArrivalState": {"Datetime": {"text": "15:54:00+09:00", "operation": "today"}}, "Destination": {"Station": {"code": "676853", "Name": "大濠公園／西鉄バス"}}, "DepartureState": {"Datetime": {"text": "15:52:00+09:00", "operation": "today"}}}, {"trainID": "187", "Name": "２・普通・西新－次郎丸－四箇田団地", "ArrivalState": {"Datetime": {"text": "15:56:00+09:00", "operation": "today"}}, "Destination": {"Station": {"code": "675272", "Name": "金武車庫／西鉄バス"}}, "DepartureState": {"Datetime": {"text": "15:54:00+09:00", "operation": "today"}}}, {"trainID": "188", "Name": "２２Ｎ・普通・病院－南公園－名島ランプ－天神", "ArrivalState": {"Datetime": {"text": "16:01:00+09:00", "operation": "today"}}, "Destination": {"Station": {"code": "676853", "Name": "大濠公園／西鉄バス"}}, "DepartureState": {"Datetime": {"text": "15:59:00+09:00", "operation": "today"}}}, {"trainID": "189", "Name": "３２・普通・志免－亀山－空港通博多駅－昭和通天神", "ArrivalState": {"Datetime": {"text": "16:11:00+09:00", "operation": "today"}}, "Destination": {"Station": {"code": "676853", "Name": "大濠公園／西鉄バス"}}, "DepartureState": {"Datetime": {"text": "16:09:00+09:00", "operation": "today"}}}, {"trainID": "190", "Name": "２７０・普通・みどりが丘－香椎参道－都高", "ArrivalState": {"Datetime": {"text": "16:11:00+09:00", "operation": "today"}}, "Destination": {"Station": {"code": "676853", "Name": "大濠公園／西鉄バス"}}, "DepartureState": {"Datetime": {"text": "16:09:00+09:00", "operation": "today"}}}, {"trainID": "191", "Name": "４・普通・八田団地－千早駅－石堂大橋－昭和通", "ArrivalState": {"Datetime": {"text": "16:12:00+09:00", "operation": "today"}}, "Destination": {"Station": {"code": "676882", "Name": "福岡タワー(ＴＮＣ放送会館前)／西鉄バス"}}, "DepartureState": {"Datetime": {"text": "16:10:00+09:00", "operation": "today"}}}, {"trainID": "192", "Name": "２－３・普通・西新－室住団地－橋本", "ArrivalState": {"Datetime": {"text": "16:13:00+09:00", "operation": "today"}}, "Destination": {"Station": {"code": "675435", "Name": "野方(営業所)／西鉄バス"}}, "DepartureState": {"Datetime": {"text": "16:11:00+09:00", "operation": "today"}}}, {"trainID": "193", "Name": "２７・普通・香椎参道－名島－昭和通－天神", "ArrivalState": {"Datetime": {"text": "16:14:00+09:00", "operation": "today"}}, "Destination": {"Station": {"code": "676853", "Name": "大濠公園／西鉄バス"}}, "DepartureState": {"Datetime": {"text": "16:12:00+09:00", "operation": "today"}}}, {"trainID": "194", "Name": "２３Ｎ・普通・香椎－海岸通り－名島ランプ－天神", "ArrivalState": {"Datetime": {"text": "16:17:00+09:00", "operation": "today"}}, "Destination": {"Station": {"code": "676853", "Name": "大濠公園／西鉄バス"}}, "DepartureState": {"Datetime": {"text": "16:15:00+09:00", "operation": "today"}}}, {"trainID": "195", "Name": "２・普通・西新－次郎丸", "ArrivalState": {"Datetime": {"text": "16:28:00+09:00", "operation": "today"}}, "Destination": {"Station": {"code": "675273", "Name": "四箇田団地／西鉄バス"}}, "DepartureState": {"Datetime": {"text": "16:26:00+09:00", "operation": "today"}}}, {"trainID": "196", "Name": "３４・普通・志免－亀山－妙見－昭和通－天神", "ArrivalState": {"Datetime": {"text": "16:31:00+09:00", "operation": "today"}}, "Destination": {"Station": {"code": "676853", "Name": "大濠公園／西鉄バス"}}, "DepartureState": {"Datetime": {"text": "16:29:00+09:00", "operation": "today"}}}, {"trainID": "197", "Name": "３０・普通・亀山－空港通－博多駅－昭和通天神", "ArrivalState": {"Datetime": {"text": "16:31:00+09:00", "operation": "today"}}, "Destination": {"Station": {"code": "676853", "Name": "大濠公園／西鉄バス"}}, "DepartureState": {"Datetime": {"text": "16:29:00+09:00", "operation": "today"}}}, {"trainID": "198", "Name": "２７Ｂ・普通・香椎参道－都高－昭和通－天神", "ArrivalState": {"Datetime": {"text": "16:31:00+09:00", "operation": "today"}}, "Destination": {"Station": {"code": "676853", "Name": "大濠公園／西鉄バス"}}, "DepartureState": {"Datetime": {"text": "16:29:00+09:00", "operation": "today"}}}, {"trainID": "199", "Name": "２２Ｎ・普通・病院－南公園－名島ランプ－天神", "ArrivalState": {"Datetime": {"text": "16:32:00+09:00", "operation": "today"}}, "Destination": {"Station": {"code": "676853", "Name": "大濠公園／西鉄バス"}}, "DepartureState": {"Datetime": {"text": "16:30:00+09:00", "operation": "today"}}}, {"trainID": "200", "Name": "２８・普通・青葉台口－香椎参道名島－昭和通－天神", "ArrivalState": {"Datetime": {"text": "16:34:00+09:00", "operation": "today"}}, "Destination": {"Station": {"code": "676853", "Name": "大濠公園／西鉄バス"}}, "DepartureState": {"Datetime": {"text": "16:32:00+09:00", "operation": "today"}}}, {"trainID": "201", "Name": "２－３・普通・西新－室住団地－橋本", "ArrivalState": {"Datetime": {"text": "16:43:00+09:00", "operation": "today"}}, "Destination": {"Station": {"code": "675435", "Name": "野方(営業所)／西鉄バス"}}, "DepartureState": {"Datetime": {"text": "16:41:00+09:00", "operation": "today"}}}, {"trainID": "202", "Name": "２３Ｎ・普通・香椎－海岸通り－名島ランプ－天神", "ArrivalState": {"Datetime": {"text": "16:47:00+09:00", "operation": "today"}}, "Destination": {"Station": {"code": "676853", "Name": "大濠公園／西鉄バス"}}, "DepartureState": {"Datetime": {"text": "16:45:00+09:00", "operation": "today"}}}, {"trainID": "203", "Name": "２８Ｂ・普通・青葉台口－香椎参道－都高－天神", "ArrivalState": {"Datetime": {"text": "16:51:00+09:00", "operation": "today"}}, "Destination": {"Station": {"code": "676853", "Name": "大濠公園／西鉄バス"}}, "DepartureState": {"Datetime": {"text": "16:49:00+09:00", "operation": "today"}}}, {"trainID": "204", "Name": "３４・普通・志免－亀山－妙見－昭和通－天神", "ArrivalState": {"Datetime": {"text": "16:51:00+09:00", "operation": "today"}}, "Destination": {"Station": {"code": "676853", "Name": "大濠公園／西鉄バス"}}, "DepartureState": {"Datetime": {"text": "16:49:00+09:00", "operation": "today"}}}, {"trainID": "205", "Name": "２２Ｎ・普通・病院－南公園－名島ランプ－天神", "ArrivalState": {"Datetime": {"text": "16:52:00+09:00", "operation": "today"}}, "Destination": {"Station": {"code": "676853", "Name": "大濠公園／西鉄バス"}}, "DepartureState": {"Datetime": {"text": "16:50:00+09:00", "operation": "today"}}}, {"trainID": "206", "Name": "２・普通・西新－田隈新町－福歯大病院", "ArrivalState": {"Datetime": {"text": "16:53:00+09:00", "operation": "today"}}, "Destination": {"Station": {"code": "675272", "Name": "金武車庫／西鉄バス"}}, "DepartureState": {"Datetime": {"text": "16:51:00+09:00", "operation": "today"}}}, {"trainID": "207", "Name": "２７・普通・香椎参道－名島－昭和通－天神", "ArrivalState": {"Datetime": {"text": "16:54:00+09:00", "operation": "today"}}, "Destination": {"Station": {"code": "676853", "Name": "大濠公園／西鉄バス"}}, "DepartureState": {"Datetime": {"text": "16:52:00+09:00", "operation": "today"}}}, {"trainID": "208", "Name": "２・普通・西新－次郎丸－四箇田団地", "ArrivalState": {"Datetime": {"text": "17:04:00+09:00", "operation": "today"}}, "Destination": {"Station": {"code": "675272", "Name": "金武車庫／西鉄バス"}}, "DepartureState": {"Datetime": {"text": "17:02:00+09:00", "operation": "today"}}}, {"trainID": "209", "Name": "４－１・普通・八田団地－千早駅－箱崎ふ頭－昭和通", "ArrivalState": {"Datetime": {"text": "17:07:00+09:00", "operation": "today"}}, "Destination": {"Station": {"code": "676882", "Name": "福岡タワー(ＴＮＣ放送会館前)／西鉄バス"}}, "DepartureState": {"Datetime": {"text": "17:05:00+09:00", "operation": "today"}}}, {"trainID": "210", "Name": "２２Ｎ・普通・病院－南公園－名島ランプ－天神", "ArrivalState": {"Datetime": {"text": "17:07:00+09:00", "operation": "today"}}, "Destination": {"Station": {"code": "676853", "Name": "大濠公園／西鉄バス"}}, "DepartureState": {"Datetime": {"text": "17:05:00+09:00", "operation": "today"}}}, {"trainID": "211", "Name": "２７０・普通・みどりが丘－香椎参道－都高", "ArrivalState": {"Datetime": {"text": "17:13:00+09:00", "operation": "today"}}, "Destination": {"Station": {"code": "676853", "Name": "大濠公園／西鉄バス"}}, "DepartureState": {"Datetime": {"text": "17:11:00+09:00", "operation": "today"}}}, {"trainID": "212", "Name": "２－３・普通・西新－室住団地－橋本", "ArrivalState": {"Datetime": {"text": "17:15:00+09:00", "operation": "today"}}, "Destination": {"Station": {"code": "675435", "Name": "野方(営業所)／西鉄バス"}}, "DepartureState": {"Datetime": {"text": "17:13:00+09:00", "operation": "today"}}}, {"trainID": "213", "Name": "２７・普通・香椎参道－名島－昭和通－天神", "ArrivalState": {"Datetime": {"text": "17:15:00+09:00", "operation": "today"}}, "Destination": {"Station": {"code": "676853", "Name": "大濠公園／西鉄バス"}}, "DepartureState": {"Datetime": {"text": "17:13:00+09:00", "operation": "today"}}}, {"trainID": "214", "Name": "２３Ｎ・普通・香椎－海岸通り－名島ランプ－天神", "ArrivalState": {"Datetime": {"text": "17:17:00+09:00", "operation": "today"}}, "Destination": {"Station": {"code": "676853", "Name": "大濠公園／西鉄バス"}}, "DepartureState": {"Datetime": {"text": "17:15:00+09:00", "operation": "today"}}}, {"trainID": "215", "Name": "２２Ｎ・普通・病院－南公園－名島ランプ－天神", "ArrivalState": {"Datetime": {"text": "17:22:00+09:00", "operation": "today"}}, "Destination": {"Station": {"code": "676853", "Name": "大濠公園／西鉄バス"}}, "DepartureState": {"Datetime": {"text": "17:20:00+09:00", "operation": "today"}}}, {"trainID": "216", "Name": "３４・普通・志免－亀山－妙見－昭和通－天神", "ArrivalState": {"Datetime": {"text": "17:23:00+09:00", "operation": "today"}}, "Destination": {"Station": {"code": "676853", "Name": "大濠公園／西鉄バス"}}, "DepartureState": {"Datetime": {"text": "17:21:00+09:00", "operation": "today"}}}, {"trainID": "217", "Name": "２・普通・西新－次郎丸", "ArrivalState": {"Datetime": {"text": "17:27:00+09:00", "operation": "today"}}, "Destination": {"Station": {"code": "675273", "Name": "四箇田団地／西鉄バス"}}, "DepartureState": {"Datetime": {"text": "17:25:00+09:00", "operation": "today"}}}, {"trainID": "218", "Name": "２７Ｂ・普通・香椎参道－都高－昭和通－天神", "ArrivalState": {"Datetime": {"text": "17:32:00+09:00", "operation": "today"}}, "Destination": {"Station": {"code": "676853", "Name": "大濠公園／西鉄バス"}}, "DepartureState": {"Datetime": {"text": "17:30:00+09:00", "operation": "today"}}}, {"trainID": "219", "Name": "２８・普通・青葉台口－香椎参道名島－昭和通－天神", "ArrivalState": {"Datetime": {"text": "17:35:00+09:00", "operation": "today"}}, "Destination": {"Station": {"code": "676853", "Name": "大濠公園／西鉄バス"}}, "DepartureState": {"Datetime": {"text": "17:33:00+09:00", "operation": "today"}}}, {"trainID": "220", "Name": "３０・普通・亀山－空港通－博多駅－昭和通天神", "ArrivalState": {"Datetime": {"text": "17:37:00+09:00", "operation": "today"}}, "Destination": {"Station": {"code": "676853", "Name": "大濠公園／西鉄バス"}}, "DepartureState": {"Datetime": {"text": "17:35:00+09:00", "operation": "today"}}}, {"trainID": "221", "Name": "３４・普通・志免－亀山－妙見－昭和通－天神", "ArrivalState": {"Datetime": {"text": "17:38:00+09:00", "operation": "today"}}, "Destination": {"Station": {"code": "676853", "Name": "大濠公園／西鉄バス"}}, "DepartureState": {"Datetime": {"text": "17:36:00+09:00", "operation": "today"}}}, {"trainID": "222", "Name": "２・普通・西新－田隈新町－福歯大病院", "ArrivalState": {"Datetime": {"text": "17:39:00+09:00", "operation": "today"}}, "Destination": {"Station": {"code": "675273", "Name": "四箇田団地／西鉄バス"}}, "DepartureState": {"Datetime": {"text": "17:37:00+09:00", "operation": "today"}}}, {"trainID": "223", "Name": "２３Ｎ・普通・香椎－海岸通り－名島ランプ－天神", "ArrivalState": {"Datetime": {"text": "17:47:00+09:00", "operation": "today"}}, "Destination": {"Station": {"code": "676853", "Name": "大濠公園／西鉄バス"}}, "DepartureState": {"Datetime": {"text": "17:45:00+09:00", "operation": "today"}}}, {"trainID": "224", "Name": "３２・普通・志免－亀山－空港通博多駅－昭和通天神", "ArrivalState": {"Datetime": {"text": "17:50:00+09:00", "operation": "today"}}, "Destination": {"Station": {"code": "676853", "Name": "大濠公園／西鉄バス"}}, "DepartureState": {"Datetime": {"text": "17:48:00+09:00", "operation": "today"}}}, {"trainID": "225", "Name": "２－３・普通・西新－室住団地－橋本", "ArrivalState": {"Datetime": {"text": "17:51:00+09:00", "operation": "today"}}, "Destination": {"Station": {"code": "675435", "Name": "野方(営業所)／西鉄バス"}}, "DepartureState": {"Datetime": {"text": "17:49:00+09:00", "operation": "today"}}}, {"trainID": "226", "Name": "２８Ｂ・普通・青葉台口－香椎参道－都高－天神", "ArrivalState": {"Datetime": {"text": "17:52:00+09:00", "operation": "today"}}, "Destination": {"Station": {"code": "676853", "Name": "大濠公園／西鉄バス"}}, "DepartureState": {"Datetime": {"text": "17:50:00+09:00", "operation": "today"}}}, {"trainID": "227", "Name": "２７・普通・香椎参道－名島－昭和通－天神", "ArrivalState": {"Datetime": {"text": "17:55:00+09:00", "operation": "today"}}, "Destination": {"Station": {"code": "676853", "Name": "大濠公園／西鉄バス"}}, "DepartureState": {"Datetime": {"text": "17:53:00+09:00", "operation": "today"}}}, {"trainID": "228", "Name": "２２Ｎ・普通・病院－南公園－名島ランプ－天神", "ArrivalState": {"Datetime": {"text": "18:02:00+09:00", "operation": "today"}}, "Destination": {"Station": {"code": "676853", "Name": "大濠公園／西鉄バス"}}, "DepartureState": {"Datetime": {"text": "18:00:00+09:00", "operation": "today"}}}, {"trainID": "229", "Name": "２・普通・西新－次郎丸－四箇田団地", "ArrivalState": {"Datetime": {"text": "18:03:00+09:00", "operation": "today"}}, "Destination": {"Station": {"code": "675272", "Name": "金武車庫／西鉄バス"}}, "DepartureState": {"Datetime": {"text": "18:01:00+09:00", "operation": "today"}}}, {"trainID": "230", "Name": "３４・普通・志免－亀山－妙見－昭和通－天神", "ArrivalState": {"Datetime": {"text": "18:03:00+09:00", "operation": "today"}}, "Destination": {"Station": {"code": "676853", "Name": "大濠公園／西鉄バス"}}, "DepartureState": {"Datetime": {"text": "18:01:00+09:00", "operation": "today"}}}, {"trainID": "231", "Name": "４－１・普通・八田団地－千早駅－箱崎ふ頭－昭和通", "ArrivalState": {"Datetime": {"text": "18:08:00+09:00", "operation": "today"}}, "Destination": {"Station": {"code": "676882", "Name": "福岡タワー(ＴＮＣ放送会館前)／西鉄バス"}}, "DepartureState": {"Datetime": {"text": "18:06:00+09:00", "operation": "today"}}}, {"trainID": "232", "Name": "２７Ｂ・普通・香椎参道－都高－昭和通－天神", "ArrivalState": {"Datetime": {"text": "18:12:00+09:00", "operation": "today"}}, "Destination": {"Station": {"code": "676853", "Name": "大濠公園／西鉄バス"}}, "DepartureState": {"Datetime": {"text": "18:10:00+09:00", "operation": "today"}}}, {"trainID": "233", "Name": "２－３・普通・西新－室住団地－橋本", "ArrivalState": {"Datetime": {"text": "18:13:00+09:00", "operation": "today"}}, "Destination": {"Station": {"code": "675435", "Name": "野方(営業所)／西鉄バス"}}, "DepartureState": {"Datetime": {"text": "18:11:00+09:00", "operation": "today"}}}, {"trainID": "234", "Name": "２７・普通・香椎参道－名島－昭和通－天神", "ArrivalState": {"Datetime": {"text": "18:15:00+09:00", "operation": "today"}}, "Destination": {"Station": {"code": "676853", "Name": "大濠公園／西鉄バス"}}, "DepartureState": {"Datetime": {"text": "18:13:00+09:00", "operation": "today"}}}, {"trainID": "235", "Name": "２３Ｎ・普通・香椎－海岸通り－名島ランプ－天神", "ArrivalState": {"Datetime": {"text": "18:17:00+09:00", "operation": "today"}}, "Destination": {"Station": {"code": "676853", "Name": "大濠公園／西鉄バス"}}, "DepartureState": {"Datetime": {"text": "18:15:00+09:00", "operation": "today"}}}, {"trainID": "236", "Name": "２・普通・西新－田隈新町－福歯大病院", "ArrivalState": {"Datetime": {"text": "18:20:00+09:00", "operation": "today"}}, "Destination": {"Station": {"code": "675272", "Name": "金武車庫／西鉄バス"}}, "DepartureState": {"Datetime": {"text": "18:18:00+09:00", "operation": "today"}}}, {"trainID": "237", "Name": "３２・普通・志免－亀山－空港通博多駅－昭和通天神", "ArrivalState": {"Datetime": {"text": "18:21:00+09:00", "operation": "today"}}, "Destination": {"Station": {"code": "676853", "Name": "大濠公園／西鉄バス"}}, "DepartureState": {"Datetime": {"text": "18:19:00+09:00", "operation": "today"}}}, {"trainID": "238", "Name": "２８Ｂ・普通・青葉台口－香椎参道－都高－天神", "ArrivalState": {"Datetime": {"text": "18:22:00+09:00", "operation": "today"}}, "Destination": {"Station": {"code": "676853", "Name": "大濠公園／西鉄バス"}}, "DepartureState": {"Datetime": {"text": "18:20:00+09:00", "operation": "today"}}}, {"trainID": "239", "Name": "３４・普通・志免－亀山－妙見－昭和通－天神", "ArrivalState": {"Datetime": {"text": "18:29:00+09:00", "operation": "today"}}, "Destination": {"Station": {"code": "676853", "Name": "大濠公園／西鉄バス"}}, "DepartureState": {"Datetime": {"text": "18:27:00+09:00", "operation": "today"}}}, {"trainID": "240", "Name": "２・普通・西新－次郎丸", "ArrivalState": {"Datetime": {"text": "18:30:00+09:00", "operation": "today"}}, "Destination": {"Station": {"code": "675273", "Name": "四箇田団地／西鉄バス"}}, "DepartureState": {"Datetime": {"text": "18:28:00+09:00", "operation": "today"}}}, {"trainID": "241", "Name": "２７０・普通・みどりが丘－香椎参道－都高", "ArrivalState": {"Datetime": {"text": "18:32:00+09:00", "operation": "today"}}, "Destination": {"Station": {"code": "676853", "Name": "大濠公園／西鉄バス"}}, "DepartureState": {"Datetime": {"text": "18:30:00+09:00", "operation": "today"}}}, {"trainID": "242", "Name": "２８・普通・青葉台口－香椎参道名島－昭和通－天神", "ArrivalState": {"Datetime": {"text": "18:35:00+09:00", "operation": "today"}}, "Destination": {"Station": {"code": "676853", "Name": "大濠公園／西鉄バス"}}, "DepartureState": {"Datetime": {"text": "18:33:00+09:00", "operation": "today"}}}, {"trainID": "243", "Name": "３４・普通・志免－亀山－妙見－昭和通－天神", "ArrivalState": {"Datetime": {"text": "18:37:00+09:00", "operation": "today"}}, "Destination": {"Station": {"code": "676853", "Name": "大濠公園／西鉄バス"}}, "DepartureState": {"Datetime": {"text": "18:35:00+09:00", "operation": "today"}}}, {"trainID": "244", "Name": "２－３・普通・西新－室住団地－橋本", "ArrivalState": {"Datetime": {"text": "18:39:00+09:00", "operation": "today"}}, "Destination": {"Station": {"code": "675435", "Name": "野方(営業所)／西鉄バス"}}, "DepartureState": {"Datetime": {"text": "18:37:00+09:00", "operation": "today"}}}, {"trainID": "245", "Name": "２３Ｎ・普通・香椎－海岸通り－名島ランプ－天神", "ArrivalState": {"Datetime": {"text": "18:47:00+09:00", "operation": "today"}}, "Destination": {"Station": {"code": "676853", "Name": "大濠公園／西鉄バス"}}, "DepartureState": {"Datetime": {"text": "18:45:00+09:00", "operation": "today"}}}, {"trainID": "246", "Name": "２・普通・西新－次郎丸－四箇田団地", "ArrivalState": {"Datetime": {"text": "18:48:00+09:00", "operation": "today"}}, "Destination": {"Station": {"code": "675272", "Name": "金武車庫／西鉄バス"}}, "DepartureState": {"Datetime": {"text": "18:46:00+09:00", "operation": "today"}}}, {"trainID": "247", "Name": "２８Ｂ・普通・青葉台口－香椎参道－都高－天神", "ArrivalState": {"Datetime": {"text": "18:53:00+09:00", "operation": "today"}}, "Destination": {"Station": {"code": "676853", "Name": "大濠公園／西鉄バス"}}, "DepartureState": {"Datetime": {"text": "18:51:00+09:00", "operation": "today"}}}, {"trainID": "248", "Name": "２７・普通・香椎参道－名島－昭和通－天神", "ArrivalState": {"Datetime": {"text": "18:55:00+09:00", "operation": "today"}}, "Destination": {"Station": {"code": "676853", "Name": "大濠公園／西鉄バス"}}, "DepartureState": {"Datetime": {"text": "18:53:00+09:00", "operation": "today"}}}, {"trainID": "249", "Name": "２－３・普通・西新－室住団地－橋本", "ArrivalState": {"Datetime": {"text": "18:58:00+09:00", "operation": "today"}}, "Destination": {"Station": {"code": "675435", "Name": "野方(営業所)／西鉄バス"}}, "DepartureState": {"Datetime": {"text": "18:56:00+09:00", "operation": "today"}}}, {"trainID": "250", "Name": "２７Ｂ・普通・香椎参道－都高－昭和通－天神", "ArrivalState": {"Datetime": {"text": "19:11:00+09:00", "operation": "today"}}, "Destination": {"Station": {"code": "676853", "Name": "大濠公園／西鉄バス"}}, "DepartureState": {"Datetime": {"text": "19:09:00+09:00", "operation": "today"}}}, {"trainID": "251", "Name": "２７・普通・香椎参道－名島－昭和通－天神", "ArrivalState": {"Datetime": {"text": "19:11:00+09:00", "operation": "today"}}, "Destination": {"Station": {"code": "676853", "Name": "大濠公園／西鉄バス"}}, "DepartureState": {"Datetime": {"text": "19:09:00+09:00", "operation": "today"}}}, {"trainID": "252", "Name": "２・普通・西新－田隈新町－福歯大病院", "ArrivalState": {"Datetime": {"text": "19:13:00+09:00", "operation": "today"}}, "Destination": {"Station": {"code": "675273", "Name": "四箇田団地／西鉄バス"}}, "DepartureState": {"Datetime": {"text": "19:11:00+09:00", "operation": "today"}}}, {"trainID": "253", "Name": "３２・普通・志免－亀山－空港通博多駅－昭和通天神", "ArrivalState": {"Datetime": {"text": "19:13:00+09:00", "operation": "today"}}, "Destination": {"Station": {"code": "676853", "Name": "大濠公園／西鉄バス"}}, "DepartureState": {"Datetime": {"text": "19:11:00+09:00", "operation": "today"}}}, {"trainID": "254", "Name": "２３Ｎ・普通・香椎－海岸通り－名島ランプ－天神", "ArrivalState": {"Datetime": {"text": "19:16:00+09:00", "operation": "today"}}, "Destination": {"Station": {"code": "676853", "Name": "大濠公園／西鉄バス"}}, "DepartureState": {"Datetime": {"text": "19:14:00+09:00", "operation": "today"}}}, {"trainID": "255", "Name": "２－３・普通・西新－室住団地－橋本", "ArrivalState": {"Datetime": {"text": "19:24:00+09:00", "operation": "today"}}, "Destination": {"Station": {"code": "675435", "Name": "野方(営業所)／西鉄バス"}}, "DepartureState": {"Datetime": {"text": "19:22:00+09:00", "operation": "today"}}}, {"trainID": "256", "Name": "２７０・普通・みどりが丘－香椎参道－都高", "ArrivalState": {"Datetime": {"text": "19:26:00+09:00", "operation": "today"}}, "Destination": {"Station": {"code": "676853", "Name": "大濠公園／西鉄バス"}}, "DepartureState": {"Datetime": {"text": "19:24:00+09:00", "operation": "today"}}}, {"trainID": "257", "Name": "２８・普通・青葉台口－香椎参道名島－昭和通－天神", "ArrivalState": {"Datetime": {"text": "19:31:00+09:00", "operation": "today"}}, "Destination": {"Station": {"code": "676853", "Name": "大濠公園／西鉄バス"}}, "DepartureState": {"Datetime": {"text": "19:29:00+09:00", "operation": "today"}}}, {"trainID": "258", "Name": "２・普通・西新－次郎丸", "ArrivalState": {"Datetime": {"text": "19:36:00+09:00", "operation": "today"}}, "Destination": {"Station": {"code": "675273", "Name": "四箇田団地／西鉄バス"}}, "DepartureState": {"Datetime": {"text": "19:34:00+09:00", "operation": "today"}}}, {"trainID": "259", "Name": "３２・普通・志免－亀山－空港通博多駅－昭和通天神", "ArrivalState": {"Datetime": {"text": "19:37:00+09:00", "operation": "today"}}, "Destination": {"Station": {"code": "676853", "Name": "大濠公園／西鉄バス"}}, "DepartureState": {"Datetime": {"text": "19:35:00+09:00", "operation": "today"}}}, {"trainID": "260", "Name": "２３Ｎ・普通・香椎－海岸通り－名島ランプ－天神", "ArrivalState": {"Datetime": {"text": "19:46:00+09:00", "operation": "today"}}, "Destination": {"Station": {"code": "676853", "Name": "大濠公園／西鉄バス"}}, "DepartureState": {"Datetime": {"text": "19:44:00+09:00", "operation": "today"}}}, {"trainID": "261", "Name": "２・普通・西新－田隈新町－福歯大病院", "ArrivalState": {"Datetime": {"text": "19:48:00+09:00", "operation": "today"}}, "Destination": {"Station": {"code": "675272", "Name": "金武車庫／西鉄バス"}}, "DepartureState": {"Datetime": {"text": "19:46:00+09:00", "operation": "today"}}}, {"trainID": "262", "Name": "２８Ｂ・普通・青葉台口－香椎参道－都高－天神", "ArrivalState": {"Datetime": {"text": "19:51:00+09:00", "operation": "today"}}, "Destination": {"Station": {"code": "676853", "Name": "大濠公園／西鉄バス"}}, "DepartureState": {"Datetime": {"text": "19:49:00+09:00", "operation": "today"}}}, {"trainID": "263", "Name": "２７・普通・香椎参道－名島－昭和通－天神", "ArrivalState": {"Datetime": {"text": "19:51:00+09:00", "operation": "today"}}, "Destination": {"Station": {"code": "676853", "Name": "大濠公園／西鉄バス"}}, "DepartureState": {"Datetime": {"text": "19:49:00+09:00", "operation": "today"}}}, {"trainID": "264", "Name": "３４・普通・志免－亀山－妙見－昭和通－天神", "ArrivalState": {"Datetime": {"text": "19:56:00+09:00", "operation": "today"}}, "Destination": {"Station": {"code": "676853", "Name": "大濠公園／西鉄バス"}}, "DepartureState": {"Datetime": {"text": "19:54:00+09:00", "operation": "today"}}}, {"trainID": "265", "Name": "２・普通・西新－田隈新町－福歯大病院", "ArrivalState": {"Datetime": {"text": "19:58:00+09:00", "operation": "today"}}, "Destination": {"Station": {"code": "675273", "Name": "四箇田団地／西鉄バス"}}, "DepartureState": {"Datetime": {"text": "19:56:00+09:00", "operation": "today"}}}, {"trainID": "266", "Name": "２２Ｎ・普通・病院－南公園－名島ランプ－天神", "ArrivalState": {"Datetime": {"text": "20:00:00+09:00", "operation": "today"}}, "Destination": {"Station": {"code": "676853", "Name": "大濠公園／西鉄バス"}}, "DepartureState": {"Datetime": {"text": "19:58:00+09:00", "operation": "today"}}}, {"trainID": "267", "Name": "２７０・普通・みどりが丘－香椎参道－都高", "ArrivalState": {"Datetime": {"text": "20:11:00+09:00", "operation": "today"}}, "Destination": {"Station": {"code": "676853", "Name": "大濠公園／西鉄バス"}}, "DepartureState": {"Datetime": {"text": "20:09:00+09:00", "operation": "today"}}}, {"trainID": "268", "Name": "２－３・普通・西新", "ArrivalState": {"Datetime": {"text": "20:13:00+09:00", "operation": "today"}}, "Destination": {"Station": {"code": "675471", "Name": "室住団地／西鉄バス"}}, "DepartureState": {"Datetime": {"text": "20:11:00+09:00", "operation": "today"}}}, {"trainID": "269", "Name": "２３Ｎ・普通・香椎－海岸通り－名島ランプ－天神", "ArrivalState": {"Datetime": {"text": "20:16:00+09:00", "operation": "today"}}, "Destination": {"Station": {"code": "676853", "Name": "大濠公園／西鉄バス"}}, "DepartureState": {"Datetime": {"text": "20:14:00+09:00", "operation": "today"}}}, {"trainID": "270", "Name": "２８・普通・青葉台口－香椎参道名島－昭和通－天神", "ArrivalState": {"Datetime": {"text": "20:31:00+09:00", "operation": "today"}}, "Destination": {"Station": {"code": "676853", "Name": "大濠公園／西鉄バス"}}, "DepartureState": {"Datetime": {"text": "20:29:00+09:00", "operation": "today"}}}, {"trainID": "271", "Name": "２７Ｂ・普通・香椎参道－都高－昭和通－天神", "ArrivalState": {"Datetime": {"text": "20:31:00+09:00", "operation": "today"}}, "Destination": {"Station": {"code": "676853", "Name": "大濠公園／西鉄バス"}}, "DepartureState": {"Datetime": {"text": "20:29:00+09:00", "operation": "today"}}}, {"trainID": "272", "Name": "２・普通・西新－次郎丸", "ArrivalState": {"Datetime": {"text": "20:32:00+09:00", "operation": "today"}}, "Destination": {"Station": {"code": "675273", "Name": "四箇田団地／西鉄バス"}}, "DepartureState": {"Datetime": {"text": "20:30:00+09:00", "operation": "today"}}}, {"trainID": "273", "Name": "２・普通・西新－田隈新町－福歯大病院", "ArrivalState": {"Datetime": {"text": "20:48:00+09:00", "operation": "today"}}, "Destination": {"Station": {"code": "675273", "Name": "四箇田団地／西鉄バス"}}, "DepartureState": {"Datetime": {"text": "20:46:00+09:00", "operation": "today"}}}, {"trainID": "274", "Name": "２７・普通・香椎参道－名島－昭和通－天神", "ArrivalState": {"Datetime": {"text": "20:51:00+09:00", "operation": "today"}}, "Destination": {"Station": {"code": "676853", "Name": "大濠公園／西鉄バス"}}, "DepartureState": {"Datetime": {"text": "20:49:00+09:00", "operation": "today"}}}, {"trainID": "275", "Name": "２８Ｂ・普通・青葉台口－香椎参道－都高－天神", "ArrivalState": {"Datetime": {"text": "21:01:00+09:00", "operation": "today"}}, "Destination": {"Station": {"code": "676853", "Name": "大濠公園／西鉄バス"}}, "DepartureState": {"Datetime": {"text": "20:59:00+09:00", "operation": "today"}}}, {"trainID": "276", "Name": "２２Ｎ・普通・病院－南公園－名島ランプ－天神", "ArrivalState": {"Datetime": {"text": "21:03:00+09:00", "operation": "today"}}, "Destination": {"Station": {"code": "676853", "Name": "大濠公園／西鉄バス"}}, "DepartureState": {"Datetime": {"text": "21:01:00+09:00", "operation": "today"}}}, {"trainID": "277", "Name": "２－３・普通・西新－室住団地－橋本", "ArrivalState": {"Datetime": {"text": "21:11:00+09:00", "operation": "today"}}, "Destination": {"Station": {"code": "675435", "Name": "野方(営業所)／西鉄バス"}}, "DepartureState": {"Datetime": {"text": "21:09:00+09:00", "operation": "today"}}}, {"trainID": "278", "Name": "２３Ｎ・普通・香椎－海岸通り－名島ランプ－天神", "ArrivalState": {"Datetime": {"text": "21:14:00+09:00", "operation": "today"}}, "Destination": {"Station": {"code": "676853", "Name": "大濠公園／西鉄バス"}}, "DepartureState": {"Datetime": {"text": "21:12:00+09:00", "operation": "today"}}}, {"trainID": "279", "Name": "３４・普通・志免－亀山－妙見－昭和通－天神", "ArrivalState": {"Datetime": {"text": "21:18:00+09:00", "operation": "today"}}, "Destination": {"Station": {"code": "676853", "Name": "大濠公園／西鉄バス"}}, "DepartureState": {"Datetime": {"text": "21:16:00+09:00", "operation": "today"}}}, {"trainID": "280", "Name": "２・普通・西新－次郎丸－四箇田団地", "ArrivalState": {"Datetime": {"text": "21:28:00+09:00", "operation": "today"}}, "Destination": {"Station": {"code": "675272", "Name": "金武車庫／西鉄バス"}}, "DepartureState": {"Datetime": {"text": "21:26:00+09:00", "operation": "today"}}}, {"trainID": "281", "Name": "２８・普通・青葉台口－香椎参道名島－昭和通－天神", "ArrivalState": {"Datetime": {"text": "21:33:00+09:00", "operation": "today"}}, "Destination": {"Station": {"code": "676853", "Name": "大濠公園／西鉄バス"}}, "DepartureState": {"Datetime": {"text": "21:31:00+09:00", "operation": "today"}}}, {"trainID": "282", "Name": "３２・普通・志免－亀山－空港通博多駅－昭和通天神", "ArrivalState": {"Datetime": {"text": "21:39:00+09:00", "operation": "today"}}, "Destination": {"Station": {"code": "676853", "Name": "大濠公園／西鉄バス"}}, "DepartureState": {"Datetime": {"text": "21:37:00+09:00", "operation": "today"}}}, {"trainID": "283", "Name": "２・普通・西新－田隈新町－福歯大病院", "ArrivalState": {"Datetime": {"text": "21:48:00+09:00", "operation": "today"}}, "Destination": {"Station": {"code": "675272", "Name": "金武車庫／西鉄バス"}}, "DepartureState": {"Datetime": {"text": "21:46:00+09:00", "operation": "today"}}}, {"trainID": "284", "Name": "２８Ｂ・普通・青葉台口－香椎参道－都高－天神", "ArrivalState": {"Datetime": {"text": "21:59:00+09:00", "operation": "today"}}, "Destination": {"Station": {"code": "676853", "Name": "大濠公園／西鉄バス"}}, "DepartureState": {"Datetime": {"text": "21:57:00+09:00", "operation": "today"}}}, {"trainID": "285", "Name": "２３Ｂ・普通", "ArrivalState": {"Datetime": {"text": "22:06:00+09:00", "operation": "today"}}, "Destination": {"Station": {"code": "676853", "Name": "大濠公園／西鉄バス"}}, "DepartureState": {"Datetime": {"text": "22:04:00+09:00", "operation": "today"}}}, {"trainID": "286", "Name": "２・普通・西新－次郎丸", "ArrivalState": {"Datetime": {"text": "22:13:00+09:00", "operation": "today"}}, "Destination": {"Station": {"code": "675273", "Name": "四箇田団地／西鉄バス"}}, "DepartureState": {"Datetime": {"text": "22:11:00+09:00", "operation": "today"}}}, {"trainID": "287", "Name": "３２・普通・志免－亀山－空港通博多駅－昭和通天神", "ArrivalState": {"Datetime": {"text": "22:19:00+09:00", "operation": "today"}}, "Destination": {"Station": {"code": "676853", "Name": "大濠公園／西鉄バス"}}, "DepartureState": {"Datetime": {"text": "22:17:00+09:00", "operation": "today"}}}, {"trainID": "288", "Name": "２－３・普通・西新－室住団地－橋本", "ArrivalState": {"Datetime": {"text": "22:28:00+09:00", "operation": "today"}}, "Destination": {"Station": {"code": "675435", "Name": "野方(営業所)／西鉄バス"}}, "DepartureState": {"Datetime": {"text": "22:26:00+09:00", "operation": "today"}}}, {"trainID": "289", "Name": "３２・普通・志免－亀山－空港通博多駅－昭和通天神", "ArrivalState": {"Datetime": {"text": "22:32:00+09:00", "operation": "today"}}, "Destination": {"Station": {"code": "676853", "Name": "大濠公園／西鉄バス"}}, "DepartureState": {"Datetime": {"text": "22:30:00+09:00", "operation": "today"}}}, {"trainID": "290", "Name": "２・普通・西新－田隈新町－福歯大病院", "ArrivalState": {"Datetime": {"text": "22:48:00+09:00", "operation": "today"}}, "Destination": {"Station": {"code": "675272", "Name": "金武車庫／西鉄バス"}}, "DepartureState": {"Datetime": {"text": "22:46:00+09:00", "operation": "today"}}}, {"trainID": "291", "Name": "３４・普通・志免－亀山－妙見－昭和通－天神", "ArrivalState": {"Datetime": {"text": "23:00:00+09:00", "operation": "today"}}, "Destination": {"Station": {"code": "676853", "Name": "大濠公園／西鉄バス"}}, "DepartureState": {"Datetime": {"text": "22:58:00+09:00", "operation": "today"}}}, {"trainID": "292", "Name": "２・普通・西新－次郎丸", "ArrivalState": {"Datetime": {"text": "23:08:00+09:00", "operation": "today"}}, "Destination": {"Station": {"code": "675273", "Name": "四箇田団地／西鉄バス"}}, "DepartureState": {"Datetime": {"text": "23:06:00+09:00", "operation": "today"}}}]}}}